<?xml version="1.0" encoding="UTF-8" ?>
<rg:Network_Data xmlns:rg="http://www.tfl.uk/CDII/Route_Geometry" xmlns:xsi="http://www.w3.org/2001/XMLSchema-instance" xsi:schemaLocation="http://www.tfl.uk/CDII/Route_Geometry ../Schema/Route_Geometry.xsd">
	<Base_Version>20220318</Base_Version>
	<Route_Geometry aContract_Line_No="209" aLBSL_Run_No="1" aSequence_No="1">
		<Direction>1</Direction>
		<Location_Easting>520973</Location_Easting>
		<Location_Northing>175745</Location_Northing>
		<Location_Longitude>-0.259781</Location_Longitude>
		<Location_Latitude>51.467752</Location_Latitude>
	</Route_Geometry>
	<Route_Geometry aContract_Line_No="209" aLBSL_Run_No="1" aSequence_No="2">
		<Direction>1</Direction>
		<Location_Easting>520977</Location_Easting>
		<Location_Northing>175757</Location_Northing>
		<Location_Longitude>-0.259719</Location_Longitude>
		<Location_Latitude>51.467859</Location_Latitude>
	</Route_Geometry>
	<Route_Geometry aContract_Line_No="209" aLBSL_Run_No="1" aSequence_No="3">
		<Direction>1</Direction>
		<Location_Easting>521006</Location_Easting>
		<Location_Northing>175768</Location_Northing>
		<Location_Longitude>-0.259298</Location_Longitude>
		<Location_Latitude>51.467952</Location_Latitude>
	</Route_Geometry>
	<Route_Geometry aContract_Line_No="209" aLBSL_Run_No="1" aSequence_No="4">
		<Direction>1</Direction>
		<Location_Easting>520959</Location_Easting>
		<Location_Northing>175977</Location_Northing>
		<Location_Longitude>-0.259903</Location_Longitude>
		<Location_Latitude>51.469840</Location_Latitude>
	</Route_Geometry>
	<Route_Geometry aContract_Line_No="209" aLBSL_Run_No="1" aSequence_No="5">
		<Direction>1</Direction>
		<Location_Easting>521126</Location_Easting>
		<Location_Northing>176017</Location_Northing>
		<Location_Longitude>-0.257486</Location_Longitude>
		<Location_Latitude>51.470164</Location_Latitude>
	</Route_Geometry>
	<Route_Geometry aContract_Line_No="209" aLBSL_Run_No="1" aSequence_No="6">
		<Direction>1</Direction>
		<Location_Easting>521235</Location_Easting>
		<Location_Northing>176066</Location_Northing>
		<Location_Longitude>-0.255901</Location_Longitude>
		<Location_Latitude>51.470581</Location_Latitude>
	</Route_Geometry>
	<Route_Geometry aContract_Line_No="209" aLBSL_Run_No="1" aSequence_No="7">
		<Direction>1</Direction>
		<Location_Easting>521259</Location_Easting>
		<Location_Northing>176115</Location_Northing>
		<Location_Longitude>-0.255539</Location_Longitude>
		<Location_Latitude>51.471016</Location_Latitude>
	</Route_Geometry>
	<Route_Geometry aContract_Line_No="209" aLBSL_Run_No="1" aSequence_No="8">
		<Direction>1</Direction>
		<Location_Easting>521433</Location_Easting>
		<Location_Northing>176270</Location_Northing>
		<Location_Longitude>-0.252982</Location_Longitude>
		<Location_Latitude>51.472372</Location_Latitude>
	</Route_Geometry>
	<Route_Geometry aContract_Line_No="209" aLBSL_Run_No="1" aSequence_No="9">
		<Direction>1</Direction>
		<Location_Easting>521542</Location_Easting>
		<Location_Northing>176408</Location_Northing>
		<Location_Longitude>-0.251366</Location_Longitude>
		<Location_Latitude>51.473589</Location_Latitude>
	</Route_Geometry>
	<Route_Geometry aContract_Line_No="209" aLBSL_Run_No="1" aSequence_No="10">
		<Direction>1</Direction>
		<Location_Easting>521575</Location_Easting>
		<Location_Northing>176401</Location_Northing>
		<Location_Longitude>-0.250893</Location_Longitude>
		<Location_Latitude>51.473519</Location_Latitude>
	</Route_Geometry>
	<Route_Geometry aContract_Line_No="209" aLBSL_Run_No="1" aSequence_No="11">
		<Direction>1</Direction>
		<Location_Easting>521676</Location_Easting>
		<Location_Northing>176431</Location_Northing>
		<Location_Longitude>-0.249429</Location_Longitude>
		<Location_Latitude>51.473767</Location_Latitude>
	</Route_Geometry>
	<Route_Geometry aContract_Line_No="209" aLBSL_Run_No="1" aSequence_No="12">
		<Direction>1</Direction>
		<Location_Easting>521703</Location_Easting>
		<Location_Northing>176427</Location_Northing>
		<Location_Longitude>-0.249042</Location_Longitude>
		<Location_Latitude>51.473725</Location_Latitude>
	</Route_Geometry>
	<Route_Geometry aContract_Line_No="209" aLBSL_Run_No="1" aSequence_No="13">
		<Direction>1</Direction>
		<Location_Easting>521794</Location_Easting>
		<Location_Northing>176387</Location_Northing>
		<Location_Longitude>-0.247746</Location_Longitude>
		<Location_Latitude>51.473346</Location_Latitude>
	</Route_Geometry>
	<Route_Geometry aContract_Line_No="209" aLBSL_Run_No="1" aSequence_No="14">
		<Direction>1</Direction>
		<Location_Easting>521836</Location_Easting>
		<Location_Northing>176400</Location_Northing>
		<Location_Longitude>-0.247138</Location_Longitude>
		<Location_Latitude>51.473454</Location_Latitude>
	</Route_Geometry>
	<Route_Geometry aContract_Line_No="209" aLBSL_Run_No="1" aSequence_No="15">
		<Direction>1</Direction>
		<Location_Easting>521966</Location_Easting>
		<Location_Northing>176473</Location_Northing>
		<Location_Longitude>-0.245241</Location_Longitude>
		<Location_Latitude>51.474082</Location_Latitude>
	</Route_Geometry>
	<Route_Geometry aContract_Line_No="209" aLBSL_Run_No="1" aSequence_No="16">
		<Direction>1</Direction>
		<Location_Easting>522048</Location_Easting>
		<Location_Northing>176479</Location_Northing>
		<Location_Longitude>-0.244059</Location_Longitude>
		<Location_Latitude>51.474119</Location_Latitude>
	</Route_Geometry>
	<Route_Geometry aContract_Line_No="209" aLBSL_Run_No="1" aSequence_No="17">
		<Direction>1</Direction>
		<Location_Easting>522137</Location_Easting>
		<Location_Northing>176522</Location_Northing>
		<Location_Longitude>-0.242764</Location_Longitude>
		<Location_Latitude>51.474486</Location_Latitude>
	</Route_Geometry>
	<Route_Geometry aContract_Line_No="209" aLBSL_Run_No="1" aSequence_No="18">
		<Direction>1</Direction>
		<Location_Easting>522233</Location_Easting>
		<Location_Northing>176551</Location_Northing>
		<Location_Longitude>-0.241372</Location_Longitude>
		<Location_Latitude>51.474726</Location_Latitude>
	</Route_Geometry>
	<Route_Geometry aContract_Line_No="209" aLBSL_Run_No="1" aSequence_No="19">
		<Direction>1</Direction>
		<Location_Easting>522289</Location_Easting>
		<Location_Northing>176586</Location_Northing>
		<Location_Longitude>-0.240554</Location_Longitude>
		<Location_Latitude>51.475028</Location_Latitude>
	</Route_Geometry>
	<Route_Geometry aContract_Line_No="209" aLBSL_Run_No="1" aSequence_No="20">
		<Direction>1</Direction>
		<Location_Easting>522379</Location_Easting>
		<Location_Northing>176613</Location_Northing>
		<Location_Longitude>-0.239249</Location_Longitude>
		<Location_Latitude>51.475251</Location_Latitude>
	</Route_Geometry>
	<Route_Geometry aContract_Line_No="209" aLBSL_Run_No="1" aSequence_No="21">
		<Direction>1</Direction>
		<Location_Easting>522378</Location_Easting>
		<Location_Northing>176634</Location_Northing>
		<Location_Longitude>-0.239256</Location_Longitude>
		<Location_Latitude>51.475441</Location_Latitude>
	</Route_Geometry>
	<Route_Geometry aContract_Line_No="209" aLBSL_Run_No="1" aSequence_No="22">
		<Direction>1</Direction>
		<Location_Easting>522579</Location_Easting>
		<Location_Northing>177443</Location_Northing>
		<Location_Longitude>-0.236083</Location_Longitude>
		<Location_Latitude>51.482668</Location_Latitude>
	</Route_Geometry>
	<Route_Geometry aContract_Line_No="209" aLBSL_Run_No="1" aSequence_No="23">
		<Direction>1</Direction>
		<Location_Easting>522594</Location_Easting>
		<Location_Northing>177477</Location_Northing>
		<Location_Longitude>-0.235856</Location_Longitude>
		<Location_Latitude>51.482970</Location_Latitude>
	</Route_Geometry>
	<Route_Geometry aContract_Line_No="209" aLBSL_Run_No="1" aSequence_No="24">
		<Direction>1</Direction>
		<Location_Easting>522608</Location_Easting>
		<Location_Northing>177501</Location_Northing>
		<Location_Longitude>-0.235646</Location_Longitude>
		<Location_Latitude>51.483183</Location_Latitude>
	</Route_Geometry>
	<Route_Geometry aContract_Line_No="209" aLBSL_Run_No="1" aSequence_No="25">
		<Direction>1</Direction>
		<Location_Easting>522735</Location_Easting>
		<Location_Northing>177706</Location_Northing>
		<Location_Longitude>-0.233747</Location_Longitude>
		<Location_Latitude>51.484998</Location_Latitude>
	</Route_Geometry>
	<Route_Geometry aContract_Line_No="209" aLBSL_Run_No="1" aSequence_No="26">
		<Direction>1</Direction>
		<Location_Easting>522791</Location_Easting>
		<Location_Northing>177797</Location_Northing>
		<Location_Longitude>-0.232909</Location_Longitude>
		<Location_Latitude>51.485803</Location_Latitude>
	</Route_Geometry>
	<Route_Geometry aContract_Line_No="209" aLBSL_Run_No="2" aSequence_No="1">
		<Direction>2</Direction>
		<Location_Easting>522791</Location_Easting>
		<Location_Northing>177797</Location_Northing>
		<Location_Longitude>-0.232909</Location_Longitude>
		<Location_Latitude>51.485803</Location_Latitude>
	</Route_Geometry>
	<Route_Geometry aContract_Line_No="209" aLBSL_Run_No="2" aSequence_No="2">
		<Direction>2</Direction>
		<Location_Easting>522735</Location_Easting>
		<Location_Northing>177706</Location_Northing>
		<Location_Longitude>-0.233747</Location_Longitude>
		<Location_Latitude>51.484998</Location_Latitude>
	</Route_Geometry>
	<Route_Geometry aContract_Line_No="209" aLBSL_Run_No="2" aSequence_No="3">
		<Direction>2</Direction>
		<Location_Easting>522608</Location_Easting>
		<Location_Northing>177501</Location_Northing>
		<Location_Longitude>-0.235646</Location_Longitude>
		<Location_Latitude>51.483183</Location_Latitude>
	</Route_Geometry>
	<Route_Geometry aContract_Line_No="209" aLBSL_Run_No="2" aSequence_No="4">
		<Direction>2</Direction>
		<Location_Easting>522594</Location_Easting>
		<Location_Northing>177477</Location_Northing>
		<Location_Longitude>-0.235856</Location_Longitude>
		<Location_Latitude>51.482970</Location_Latitude>
	</Route_Geometry>
	<Route_Geometry aContract_Line_No="209" aLBSL_Run_No="2" aSequence_No="5">
		<Direction>2</Direction>
		<Location_Easting>522579</Location_Easting>
		<Location_Northing>177443</Location_Northing>
		<Location_Longitude>-0.236083</Location_Longitude>
		<Location_Latitude>51.482668</Location_Latitude>
	</Route_Geometry>
	<Route_Geometry aContract_Line_No="209" aLBSL_Run_No="2" aSequence_No="6">
		<Direction>2</Direction>
		<Location_Easting>522378</Location_Easting>
		<Location_Northing>176634</Location_Northing>
		<Location_Longitude>-0.239256</Location_Longitude>
		<Location_Latitude>51.475441</Location_Latitude>
	</Route_Geometry>
	<Route_Geometry aContract_Line_No="209" aLBSL_Run_No="2" aSequence_No="7">
		<Direction>2</Direction>
		<Location_Easting>522379</Location_Easting>
		<Location_Northing>176613</Location_Northing>
		<Location_Longitude>-0.239249</Location_Longitude>
		<Location_Latitude>51.475251</Location_Latitude>
	</Route_Geometry>
	<Route_Geometry aContract_Line_No="209" aLBSL_Run_No="2" aSequence_No="8">
		<Direction>2</Direction>
		<Location_Easting>522289</Location_Easting>
		<Location_Northing>176586</Location_Northing>
		<Location_Longitude>-0.240554</Location_Longitude>
		<Location_Latitude>51.475028</Location_Latitude>
	</Route_Geometry>
	<Route_Geometry aContract_Line_No="209" aLBSL_Run_No="2" aSequence_No="9">
		<Direction>2</Direction>
		<Location_Easting>522233</Location_Easting>
		<Location_Northing>176551</Location_Northing>
		<Location_Longitude>-0.241372</Location_Longitude>
		<Location_Latitude>51.474726</Location_Latitude>
	</Route_Geometry>
	<Route_Geometry aContract_Line_No="209" aLBSL_Run_No="2" aSequence_No="10">
		<Direction>2</Direction>
		<Location_Easting>522137</Location_Easting>
		<Location_Northing>176522</Location_Northing>
		<Location_Longitude>-0.242764</Location_Longitude>
		<Location_Latitude>51.474486</Location_Latitude>
	</Route_Geometry>
	<Route_Geometry aContract_Line_No="209" aLBSL_Run_No="2" aSequence_No="11">
		<Direction>2</Direction>
		<Location_Easting>522048</Location_Easting>
		<Location_Northing>176479</Location_Northing>
		<Location_Longitude>-0.244059</Location_Longitude>
		<Location_Latitude>51.474119</Location_Latitude>
	</Route_Geometry>
	<Route_Geometry aContract_Line_No="209" aLBSL_Run_No="2" aSequence_No="12">
		<Direction>2</Direction>
		<Location_Easting>521966</Location_Easting>
		<Location_Northing>176473</Location_Northing>
		<Location_Longitude>-0.245241</Location_Longitude>
		<Location_Latitude>51.474082</Location_Latitude>
	</Route_Geometry>
	<Route_Geometry aContract_Line_No="209" aLBSL_Run_No="2" aSequence_No="13">
		<Direction>2</Direction>
		<Location_Easting>521836</Location_Easting>
		<Location_Northing>176400</Location_Northing>
		<Location_Longitude>-0.247138</Location_Longitude>
		<Location_Latitude>51.473454</Location_Latitude>
	</Route_Geometry>
	<Route_Geometry aContract_Line_No="209" aLBSL_Run_No="2" aSequence_No="14">
		<Direction>2</Direction>
		<Location_Easting>521794</Location_Easting>
		<Location_Northing>176387</Location_Northing>
		<Location_Longitude>-0.247746</Location_Longitude>
		<Location_Latitude>51.473346</Location_Latitude>
	</Route_Geometry>
	<Route_Geometry aContract_Line_No="209" aLBSL_Run_No="2" aSequence_No="15">
		<Direction>2</Direction>
		<Location_Easting>521703</Location_Easting>
		<Location_Northing>176427</Location_Northing>
		<Location_Longitude>-0.249042</Location_Longitude>
		<Location_Latitude>51.473725</Location_Latitude>
	</Route_Geometry>
	<Route_Geometry aContract_Line_No="209" aLBSL_Run_No="2" aSequence_No="16">
		<Direction>2</Direction>
		<Location_Easting>521676</Location_Easting>
		<Location_Northing>176431</Location_Northing>
		<Location_Longitude>-0.249429</Location_Longitude>
		<Location_Latitude>51.473767</Location_Latitude>
	</Route_Geometry>
	<Route_Geometry aContract_Line_No="209" aLBSL_Run_No="2" aSequence_No="17">
		<Direction>2</Direction>
		<Location_Easting>521575</Location_Easting>
		<Location_Northing>176401</Location_Northing>
		<Location_Longitude>-0.250893</Location_Longitude>
		<Location_Latitude>51.473519</Location_Latitude>
	</Route_Geometry>
	<Route_Geometry aContract_Line_No="209" aLBSL_Run_No="2" aSequence_No="18">
		<Direction>2</Direction>
		<Location_Easting>521542</Location_Easting>
		<Location_Northing>176408</Location_Northing>
		<Location_Longitude>-0.251366</Location_Longitude>
		<Location_Latitude>51.473589</Location_Latitude>
	</Route_Geometry>
	<Route_Geometry aContract_Line_No="209" aLBSL_Run_No="2" aSequence_No="19">
		<Direction>2</Direction>
		<Location_Easting>521433</Location_Easting>
		<Location_Northing>176270</Location_Northing>
		<Location_Longitude>-0.252982</Location_Longitude>
		<Location_Latitude>51.472372</Location_Latitude>
	</Route_Geometry>
	<Route_Geometry aContract_Line_No="209" aLBSL_Run_No="2" aSequence_No="20">
		<Direction>2</Direction>
		<Location_Easting>521259</Location_Easting>
		<Location_Northing>176115</Location_Northing>
		<Location_Longitude>-0.255539</Location_Longitude>
		<Location_Latitude>51.471016</Location_Latitude>
	</Route_Geometry>
	<Route_Geometry aContract_Line_No="209" aLBSL_Run_No="2" aSequence_No="21">
		<Direction>2</Direction>
		<Location_Easting>521235</Location_Easting>
		<Location_Northing>176066</Location_Northing>
		<Location_Longitude>-0.255901</Location_Longitude>
		<Location_Latitude>51.470581</Location_Latitude>
	</Route_Geometry>
	<Route_Geometry aContract_Line_No="209" aLBSL_Run_No="2" aSequence_No="22">
		<Direction>2</Direction>
		<Location_Easting>521126</Location_Easting>
		<Location_Northing>176017</Location_Northing>
		<Location_Longitude>-0.257486</Location_Longitude>
		<Location_Latitude>51.470164</Location_Latitude>
	</Route_Geometry>
	<Route_Geometry aContract_Line_No="209" aLBSL_Run_No="2" aSequence_No="23">
		<Direction>2</Direction>
		<Location_Easting>520959</Location_Easting>
		<Location_Northing>175977</Location_Northing>
		<Location_Longitude>-0.259903</Location_Longitude>
		<Location_Latitude>51.469840</Location_Latitude>
	</Route_Geometry>
	<Route_Geometry aContract_Line_No="209" aLBSL_Run_No="2" aSequence_No="24">
		<Direction>2</Direction>
		<Location_Easting>520983</Location_Easting>
		<Location_Northing>175872</Location_Northing>
		<Location_Longitude>-0.259594</Location_Longitude>
		<Location_Latitude>51.468891</Location_Latitude>
	</Route_Geometry>
	<Route_Geometry aContract_Line_No="209" aLBSL_Run_No="2" aSequence_No="25">
		<Direction>2</Direction>
		<Location_Easting>521006</Location_Easting>
		<Location_Northing>175768</Location_Northing>
		<Location_Longitude>-0.259298</Location_Longitude>
		<Location_Latitude>51.467952</Location_Latitude>
	</Route_Geometry>
</rg:Network_Data>
