<?xml version="1.0" encoding="UTF-8" ?>
<rg:Network_Data xmlns:rg="http://www.tfl.uk/CDII/Route_Geometry" xmlns:xsi="http://www.w3.org/2001/XMLSchema-instance" xsi:schemaLocation="http://www.tfl.uk/CDII/Route_Geometry ../Schema/Route_Geometry.xsd">
	<Base_Version>20220318</Base_Version>
	<Route_Geometry aContract_Line_No="X140" aLBSL_Run_No="1" aSequence_No="1">
		<Direction>1</Direction>
		<Location_Easting>507551</Location_Easting>
		<Location_Northing>175848</Location_Northing>
		<Location_Longitude>-0.452902</Location_Longitude>
		<Location_Latitude>51.471386</Location_Latitude>
	</Route_Geometry>
	<Route_Geometry aContract_Line_No="X140" aLBSL_Run_No="1" aSequence_No="2">
		<Direction>1</Direction>
		<Location_Easting>507486</Location_Easting>
		<Location_Northing>175849</Location_Northing>
		<Location_Longitude>-0.453837</Location_Longitude>
		<Location_Latitude>51.471407</Location_Latitude>
	</Route_Geometry>
	<Route_Geometry aContract_Line_No="X140" aLBSL_Run_No="1" aSequence_No="3">
		<Direction>1</Direction>
		<Location_Easting>507473</Location_Easting>
		<Location_Northing>175824</Location_Northing>
		<Location_Longitude>-0.454032</Location_Longitude>
		<Location_Latitude>51.471185</Location_Latitude>
	</Route_Geometry>
	<Route_Geometry aContract_Line_No="X140" aLBSL_Run_No="1" aSequence_No="4">
		<Direction>1</Direction>
		<Location_Easting>507446</Location_Easting>
		<Location_Northing>175824</Location_Northing>
		<Location_Longitude>-0.454420</Location_Longitude>
		<Location_Latitude>51.471190</Location_Latitude>
	</Route_Geometry>
	<Route_Geometry aContract_Line_No="X140" aLBSL_Run_No="1" aSequence_No="5">
		<Direction>1</Direction>
		<Location_Easting>507473</Location_Easting>
		<Location_Northing>175896</Location_Northing>
		<Location_Longitude>-0.454010</Location_Longitude>
		<Location_Latitude>51.471832</Location_Latitude>
	</Route_Geometry>
	<Route_Geometry aContract_Line_No="X140" aLBSL_Run_No="1" aSequence_No="6">
		<Direction>1</Direction>
		<Location_Easting>507506</Location_Easting>
		<Location_Northing>175931</Location_Northing>
		<Location_Longitude>-0.453524</Location_Longitude>
		<Location_Latitude>51.472141</Location_Latitude>
	</Route_Geometry>
	<Route_Geometry aContract_Line_No="X140" aLBSL_Run_No="1" aSequence_No="7">
		<Direction>1</Direction>
		<Location_Easting>507528</Location_Easting>
		<Location_Northing>175975</Location_Northing>
		<Location_Longitude>-0.453194</Location_Longitude>
		<Location_Latitude>51.472532</Location_Latitude>
	</Route_Geometry>
	<Route_Geometry aContract_Line_No="X140" aLBSL_Run_No="1" aSequence_No="8">
		<Direction>1</Direction>
		<Location_Easting>507538</Location_Easting>
		<Location_Northing>176178</Location_Northing>
		<Location_Longitude>-0.452989</Location_Longitude>
		<Location_Latitude>51.474355</Location_Latitude>
	</Route_Geometry>
	<Route_Geometry aContract_Line_No="X140" aLBSL_Run_No="1" aSequence_No="9">
		<Direction>1</Direction>
		<Location_Easting>507520</Location_Easting>
		<Location_Northing>176829</Location_Northing>
		<Location_Longitude>-0.453050</Location_Longitude>
		<Location_Latitude>51.480209</Location_Latitude>
	</Route_Geometry>
	<Route_Geometry aContract_Line_No="X140" aLBSL_Run_No="1" aSequence_No="10">
		<Direction>1</Direction>
		<Location_Easting>507496</Location_Easting>
		<Location_Northing>176864</Location_Northing>
		<Location_Longitude>-0.453385</Location_Longitude>
		<Location_Latitude>51.480529</Location_Latitude>
	</Route_Geometry>
	<Route_Geometry aContract_Line_No="X140" aLBSL_Run_No="1" aSequence_No="11">
		<Direction>1</Direction>
		<Location_Easting>507482</Location_Easting>
		<Location_Northing>176916</Location_Northing>
		<Location_Longitude>-0.453571</Location_Longitude>
		<Location_Latitude>51.480999</Location_Latitude>
	</Route_Geometry>
	<Route_Geometry aContract_Line_No="X140" aLBSL_Run_No="1" aSequence_No="12">
		<Direction>1</Direction>
		<Location_Easting>507485</Location_Easting>
		<Location_Northing>177000</Location_Northing>
		<Location_Longitude>-0.453502</Location_Longitude>
		<Location_Latitude>51.481753</Location_Latitude>
	</Route_Geometry>
	<Route_Geometry aContract_Line_No="X140" aLBSL_Run_No="1" aSequence_No="13">
		<Direction>1</Direction>
		<Location_Easting>507495</Location_Easting>
		<Location_Northing>177022</Location_Northing>
		<Location_Longitude>-0.453351</Location_Longitude>
		<Location_Latitude>51.481949</Location_Latitude>
	</Route_Geometry>
	<Route_Geometry aContract_Line_No="X140" aLBSL_Run_No="1" aSequence_No="14">
		<Direction>1</Direction>
		<Location_Easting>507528</Location_Easting>
		<Location_Northing>177035</Location_Northing>
		<Location_Longitude>-0.452872</Location_Longitude>
		<Location_Latitude>51.482060</Location_Latitude>
	</Route_Geometry>
	<Route_Geometry aContract_Line_No="X140" aLBSL_Run_No="1" aSequence_No="15">
		<Direction>1</Direction>
		<Location_Easting>507553</Location_Easting>
		<Location_Northing>177030</Location_Northing>
		<Location_Longitude>-0.452514</Location_Longitude>
		<Location_Latitude>51.482010</Location_Latitude>
	</Route_Geometry>
	<Route_Geometry aContract_Line_No="X140" aLBSL_Run_No="1" aSequence_No="16">
		<Direction>1</Direction>
		<Location_Easting>507613</Location_Easting>
		<Location_Northing>176986</Location_Northing>
		<Location_Longitude>-0.451664</Location_Longitude>
		<Location_Latitude>51.481603</Location_Latitude>
	</Route_Geometry>
	<Route_Geometry aContract_Line_No="X140" aLBSL_Run_No="1" aSequence_No="17">
		<Direction>1</Direction>
		<Location_Easting>507728</Location_Easting>
		<Location_Northing>176970</Location_Northing>
		<Location_Longitude>-0.450013</Location_Longitude>
		<Location_Latitude>51.481437</Location_Latitude>
	</Route_Geometry>
	<Route_Geometry aContract_Line_No="X140" aLBSL_Run_No="1" aSequence_No="18">
		<Direction>1</Direction>
		<Location_Easting>507742</Location_Easting>
		<Location_Northing>176957</Location_Northing>
		<Location_Longitude>-0.449816</Location_Longitude>
		<Location_Latitude>51.481318</Location_Latitude>
	</Route_Geometry>
	<Route_Geometry aContract_Line_No="X140" aLBSL_Run_No="1" aSequence_No="19">
		<Direction>1</Direction>
		<Location_Easting>508796</Location_Easting>
		<Location_Northing>176920</Location_Northing>
		<Location_Longitude>-0.434654</Location_Longitude>
		<Location_Latitude>51.480783</Location_Latitude>
	</Route_Geometry>
	<Route_Geometry aContract_Line_No="X140" aLBSL_Run_No="1" aSequence_No="20">
		<Direction>1</Direction>
		<Location_Easting>508811</Location_Easting>
		<Location_Northing>176933</Location_Northing>
		<Location_Longitude>-0.434434</Location_Longitude>
		<Location_Latitude>51.480897</Location_Latitude>
	</Route_Geometry>
	<Route_Geometry aContract_Line_No="X140" aLBSL_Run_No="1" aSequence_No="21">
		<Direction>1</Direction>
		<Location_Easting>508826</Location_Easting>
		<Location_Northing>177225</Location_Northing>
		<Location_Longitude>-0.434129</Location_Longitude>
		<Location_Latitude>51.483519</Location_Latitude>
	</Route_Geometry>
	<Route_Geometry aContract_Line_No="X140" aLBSL_Run_No="1" aSequence_No="22">
		<Direction>1</Direction>
		<Location_Easting>508809</Location_Easting>
		<Location_Northing>177363</Location_Northing>
		<Location_Longitude>-0.434331</Location_Longitude>
		<Location_Latitude>51.484763</Location_Latitude>
	</Route_Geometry>
	<Route_Geometry aContract_Line_No="X140" aLBSL_Run_No="1" aSequence_No="23">
		<Direction>1</Direction>
		<Location_Easting>508775</Location_Easting>
		<Location_Northing>177464</Location_Northing>
		<Location_Longitude>-0.434789</Location_Longitude>
		<Location_Latitude>51.485677</Location_Latitude>
	</Route_Geometry>
	<Route_Geometry aContract_Line_No="X140" aLBSL_Run_No="1" aSequence_No="24">
		<Direction>1</Direction>
		<Location_Easting>508712</Location_Easting>
		<Location_Northing>177605</Location_Northing>
		<Location_Longitude>-0.435653</Location_Longitude>
		<Location_Latitude>51.486957</Location_Latitude>
	</Route_Geometry>
	<Route_Geometry aContract_Line_No="X140" aLBSL_Run_No="1" aSequence_No="25">
		<Direction>1</Direction>
		<Location_Easting>508696</Location_Easting>
		<Location_Northing>177702</Location_Northing>
		<Location_Longitude>-0.435854</Location_Longitude>
		<Location_Latitude>51.487832</Location_Latitude>
	</Route_Geometry>
	<Route_Geometry aContract_Line_No="X140" aLBSL_Run_No="1" aSequence_No="26">
		<Direction>1</Direction>
		<Location_Easting>508794</Location_Easting>
		<Location_Northing>178090</Location_Northing>
		<Location_Longitude>-0.434323</Location_Longitude>
		<Location_Latitude>51.491300</Location_Latitude>
	</Route_Geometry>
	<Route_Geometry aContract_Line_No="X140" aLBSL_Run_No="1" aSequence_No="27">
		<Direction>1</Direction>
		<Location_Easting>508830</Location_Easting>
		<Location_Northing>178132</Location_Northing>
		<Location_Longitude>-0.433792</Location_Longitude>
		<Location_Latitude>51.491671</Location_Latitude>
	</Route_Geometry>
	<Route_Geometry aContract_Line_No="X140" aLBSL_Run_No="1" aSequence_No="28">
		<Direction>1</Direction>
		<Location_Easting>508870</Location_Easting>
		<Location_Northing>178155</Location_Northing>
		<Location_Longitude>-0.433209</Location_Longitude>
		<Location_Latitude>51.491870</Location_Latitude>
	</Route_Geometry>
	<Route_Geometry aContract_Line_No="X140" aLBSL_Run_No="1" aSequence_No="29">
		<Direction>1</Direction>
		<Location_Easting>509076</Location_Easting>
		<Location_Northing>178194</Location_Northing>
		<Location_Longitude>-0.430231</Location_Longitude>
		<Location_Latitude>51.492181</Location_Latitude>
	</Route_Geometry>
	<Route_Geometry aContract_Line_No="X140" aLBSL_Run_No="1" aSequence_No="30">
		<Direction>1</Direction>
		<Location_Easting>509107</Location_Easting>
		<Location_Northing>178209</Location_Northing>
		<Location_Longitude>-0.429780</Location_Longitude>
		<Location_Latitude>51.492309</Location_Latitude>
	</Route_Geometry>
	<Route_Geometry aContract_Line_No="X140" aLBSL_Run_No="1" aSequence_No="31">
		<Direction>1</Direction>
		<Location_Easting>509154</Location_Easting>
		<Location_Northing>178259</Location_Northing>
		<Location_Longitude>-0.429088</Location_Longitude>
		<Location_Latitude>51.492750</Location_Latitude>
	</Route_Geometry>
	<Route_Geometry aContract_Line_No="X140" aLBSL_Run_No="1" aSequence_No="32">
		<Direction>1</Direction>
		<Location_Easting>509168</Location_Easting>
		<Location_Northing>178287</Location_Northing>
		<Location_Longitude>-0.428878</Location_Longitude>
		<Location_Latitude>51.492999</Location_Latitude>
	</Route_Geometry>
	<Route_Geometry aContract_Line_No="X140" aLBSL_Run_No="1" aSequence_No="33">
		<Direction>1</Direction>
		<Location_Easting>509201</Location_Easting>
		<Location_Northing>178500</Location_Northing>
		<Location_Longitude>-0.428336</Location_Longitude>
		<Location_Latitude>51.494907</Location_Latitude>
	</Route_Geometry>
	<Route_Geometry aContract_Line_No="X140" aLBSL_Run_No="1" aSequence_No="34">
		<Direction>1</Direction>
		<Location_Easting>509270</Location_Easting>
		<Location_Northing>178734</Location_Northing>
		<Location_Longitude>-0.427271</Location_Longitude>
		<Location_Latitude>51.496997</Location_Latitude>
	</Route_Geometry>
	<Route_Geometry aContract_Line_No="X140" aLBSL_Run_No="1" aSequence_No="35">
		<Direction>1</Direction>
		<Location_Easting>509396</Location_Easting>
		<Location_Northing>179000</Location_Northing>
		<Location_Longitude>-0.425374</Location_Longitude>
		<Location_Latitude>51.499363</Location_Latitude>
	</Route_Geometry>
	<Route_Geometry aContract_Line_No="X140" aLBSL_Run_No="1" aSequence_No="36">
		<Direction>1</Direction>
		<Location_Easting>509497</Location_Easting>
		<Location_Northing>179241</Location_Northing>
		<Location_Longitude>-0.423844</Location_Longitude>
		<Location_Latitude>51.501510</Location_Latitude>
	</Route_Geometry>
	<Route_Geometry aContract_Line_No="X140" aLBSL_Run_No="1" aSequence_No="37">
		<Direction>1</Direction>
		<Location_Easting>509535</Location_Easting>
		<Location_Northing>179280</Location_Northing>
		<Location_Longitude>-0.423285</Location_Longitude>
		<Location_Latitude>51.501853</Location_Latitude>
	</Route_Geometry>
	<Route_Geometry aContract_Line_No="X140" aLBSL_Run_No="1" aSequence_No="38">
		<Direction>1</Direction>
		<Location_Easting>509660</Location_Easting>
		<Location_Northing>179365</Location_Northing>
		<Location_Longitude>-0.421459</Location_Longitude>
		<Location_Latitude>51.502593</Location_Latitude>
	</Route_Geometry>
	<Route_Geometry aContract_Line_No="X140" aLBSL_Run_No="1" aSequence_No="39">
		<Direction>1</Direction>
		<Location_Easting>509715</Location_Easting>
		<Location_Northing>179446</Location_Northing>
		<Location_Longitude>-0.420641</Location_Longitude>
		<Location_Latitude>51.503310</Location_Latitude>
	</Route_Geometry>
	<Route_Geometry aContract_Line_No="X140" aLBSL_Run_No="1" aSequence_No="40">
		<Direction>1</Direction>
		<Location_Easting>509817</Location_Easting>
		<Location_Northing>179670</Location_Northing>
		<Location_Longitude>-0.419103</Location_Longitude>
		<Location_Latitude>51.505304</Location_Latitude>
	</Route_Geometry>
	<Route_Geometry aContract_Line_No="X140" aLBSL_Run_No="1" aSequence_No="41">
		<Direction>1</Direction>
		<Location_Easting>509819</Location_Easting>
		<Location_Northing>179809</Location_Northing>
		<Location_Longitude>-0.419031</Location_Longitude>
		<Location_Latitude>51.506553</Location_Latitude>
	</Route_Geometry>
	<Route_Geometry aContract_Line_No="X140" aLBSL_Run_No="1" aSequence_No="42">
		<Direction>1</Direction>
		<Location_Easting>509828</Location_Easting>
		<Location_Northing>179858</Location_Northing>
		<Location_Longitude>-0.418886</Location_Longitude>
		<Location_Latitude>51.506991</Location_Latitude>
	</Route_Geometry>
	<Route_Geometry aContract_Line_No="X140" aLBSL_Run_No="1" aSequence_No="43">
		<Direction>1</Direction>
		<Location_Easting>509843</Location_Easting>
		<Location_Northing>179876</Location_Northing>
		<Location_Longitude>-0.418664</Location_Longitude>
		<Location_Latitude>51.507150</Location_Latitude>
	</Route_Geometry>
	<Route_Geometry aContract_Line_No="X140" aLBSL_Run_No="1" aSequence_No="44">
		<Direction>1</Direction>
		<Location_Easting>509890</Location_Easting>
		<Location_Northing>179892</Location_Northing>
		<Location_Longitude>-0.417982</Location_Longitude>
		<Location_Latitude>51.507285</Location_Latitude>
	</Route_Geometry>
	<Route_Geometry aContract_Line_No="X140" aLBSL_Run_No="1" aSequence_No="45">
		<Direction>1</Direction>
		<Location_Easting>509899</Location_Easting>
		<Location_Northing>179903</Location_Northing>
		<Location_Longitude>-0.417849</Location_Longitude>
		<Location_Latitude>51.507382</Location_Latitude>
	</Route_Geometry>
	<Route_Geometry aContract_Line_No="X140" aLBSL_Run_No="1" aSequence_No="46">
		<Direction>1</Direction>
		<Location_Easting>509906</Location_Easting>
		<Location_Northing>179898</Location_Northing>
		<Location_Longitude>-0.417750</Location_Longitude>
		<Location_Latitude>51.507336</Location_Latitude>
	</Route_Geometry>
	<Route_Geometry aContract_Line_No="X140" aLBSL_Run_No="1" aSequence_No="47">
		<Direction>1</Direction>
		<Location_Easting>509937</Location_Easting>
		<Location_Northing>179918</Location_Northing>
		<Location_Longitude>-0.417297</Location_Longitude>
		<Location_Latitude>51.507510</Location_Latitude>
	</Route_Geometry>
	<Route_Geometry aContract_Line_No="X140" aLBSL_Run_No="1" aSequence_No="48">
		<Direction>1</Direction>
		<Location_Easting>509992</Location_Easting>
		<Location_Northing>179979</Location_Northing>
		<Location_Longitude>-0.416486</Location_Longitude>
		<Location_Latitude>51.508047</Location_Latitude>
	</Route_Geometry>
	<Route_Geometry aContract_Line_No="X140" aLBSL_Run_No="1" aSequence_No="49">
		<Direction>1</Direction>
		<Location_Easting>510115</Location_Easting>
		<Location_Northing>180193</Location_Northing>
		<Location_Longitude>-0.414648</Location_Longitude>
		<Location_Latitude>51.509947</Location_Latitude>
	</Route_Geometry>
	<Route_Geometry aContract_Line_No="X140" aLBSL_Run_No="1" aSequence_No="50">
		<Direction>1</Direction>
		<Location_Easting>510147</Location_Easting>
		<Location_Northing>180229</Location_Northing>
		<Location_Longitude>-0.414176</Location_Longitude>
		<Location_Latitude>51.510264</Location_Latitude>
	</Route_Geometry>
	<Route_Geometry aContract_Line_No="X140" aLBSL_Run_No="1" aSequence_No="51">
		<Direction>1</Direction>
		<Location_Easting>510278</Location_Easting>
		<Location_Northing>180455</Location_Northing>
		<Location_Longitude>-0.412218</Location_Longitude>
		<Location_Latitude>51.512270</Location_Latitude>
	</Route_Geometry>
	<Route_Geometry aContract_Line_No="X140" aLBSL_Run_No="1" aSequence_No="52">
		<Direction>1</Direction>
		<Location_Easting>510324</Location_Easting>
		<Location_Northing>180556</Location_Northing>
		<Location_Longitude>-0.411524</Location_Longitude>
		<Location_Latitude>51.513169</Location_Latitude>
	</Route_Geometry>
	<Route_Geometry aContract_Line_No="X140" aLBSL_Run_No="1" aSequence_No="53">
		<Direction>1</Direction>
		<Location_Easting>510378</Location_Easting>
		<Location_Northing>180650</Location_Northing>
		<Location_Longitude>-0.410716</Location_Longitude>
		<Location_Latitude>51.514003</Location_Latitude>
	</Route_Geometry>
	<Route_Geometry aContract_Line_No="X140" aLBSL_Run_No="1" aSequence_No="54">
		<Direction>1</Direction>
		<Location_Easting>510521</Location_Easting>
		<Location_Northing>180949</Location_Northing>
		<Location_Longitude>-0.408563</Location_Longitude>
		<Location_Latitude>51.516663</Location_Latitude>
	</Route_Geometry>
	<Route_Geometry aContract_Line_No="X140" aLBSL_Run_No="1" aSequence_No="55">
		<Direction>1</Direction>
		<Location_Easting>510544</Location_Easting>
		<Location_Northing>180983</Location_Northing>
		<Location_Longitude>-0.408221</Location_Longitude>
		<Location_Latitude>51.516964</Location_Latitude>
	</Route_Geometry>
	<Route_Geometry aContract_Line_No="X140" aLBSL_Run_No="1" aSequence_No="56">
		<Direction>1</Direction>
		<Location_Easting>510602</Location_Easting>
		<Location_Northing>181028</Location_Northing>
		<Location_Longitude>-0.407371</Location_Longitude>
		<Location_Latitude>51.517357</Location_Latitude>
	</Route_Geometry>
	<Route_Geometry aContract_Line_No="X140" aLBSL_Run_No="1" aSequence_No="57">
		<Direction>1</Direction>
		<Location_Easting>510627</Location_Easting>
		<Location_Northing>181063</Location_Northing>
		<Location_Longitude>-0.407000</Location_Longitude>
		<Location_Latitude>51.517666</Location_Latitude>
	</Route_Geometry>
	<Route_Geometry aContract_Line_No="X140" aLBSL_Run_No="1" aSequence_No="58">
		<Direction>1</Direction>
		<Location_Easting>510745</Location_Easting>
		<Location_Northing>181307</Location_Northing>
		<Location_Longitude>-0.405223</Location_Longitude>
		<Location_Latitude>51.519836</Location_Latitude>
	</Route_Geometry>
	<Route_Geometry aContract_Line_No="X140" aLBSL_Run_No="1" aSequence_No="59">
		<Direction>1</Direction>
		<Location_Easting>510862</Location_Easting>
		<Location_Northing>181419</Location_Northing>
		<Location_Longitude>-0.403502</Location_Longitude>
		<Location_Latitude>51.520820</Location_Latitude>
	</Route_Geometry>
	<Route_Geometry aContract_Line_No="X140" aLBSL_Run_No="1" aSequence_No="60">
		<Direction>1</Direction>
		<Location_Easting>510986</Location_Easting>
		<Location_Northing>181558</Location_Northing>
		<Location_Longitude>-0.401672</Location_Longitude>
		<Location_Latitude>51.522045</Location_Latitude>
	</Route_Geometry>
	<Route_Geometry aContract_Line_No="X140" aLBSL_Run_No="1" aSequence_No="61">
		<Direction>1</Direction>
		<Location_Easting>511097</Location_Easting>
		<Location_Northing>181721</Location_Northing>
		<Location_Longitude>-0.400021</Location_Longitude>
		<Location_Latitude>51.523488</Location_Latitude>
	</Route_Geometry>
	<Route_Geometry aContract_Line_No="X140" aLBSL_Run_No="1" aSequence_No="62">
		<Direction>1</Direction>
		<Location_Easting>511154</Location_Easting>
		<Location_Northing>181875</Location_Northing>
		<Location_Longitude>-0.399152</Location_Longitude>
		<Location_Latitude>51.524861</Location_Latitude>
	</Route_Geometry>
	<Route_Geometry aContract_Line_No="X140" aLBSL_Run_No="1" aSequence_No="63">
		<Direction>1</Direction>
		<Location_Easting>511160</Location_Easting>
		<Location_Northing>182000</Location_Northing>
		<Location_Longitude>-0.399026</Location_Longitude>
		<Location_Latitude>51.525983</Location_Latitude>
	</Route_Geometry>
	<Route_Geometry aContract_Line_No="X140" aLBSL_Run_No="1" aSequence_No="64">
		<Direction>1</Direction>
		<Location_Easting>511141</Location_Easting>
		<Location_Northing>182169</Location_Northing>
		<Location_Longitude>-0.399246</Location_Longitude>
		<Location_Latitude>51.527506</Location_Latitude>
	</Route_Geometry>
	<Route_Geometry aContract_Line_No="X140" aLBSL_Run_No="1" aSequence_No="65">
		<Direction>1</Direction>
		<Location_Easting>511134</Location_Easting>
		<Location_Northing>182177</Location_Northing>
		<Location_Longitude>-0.399345</Location_Longitude>
		<Location_Latitude>51.527579</Location_Latitude>
	</Route_Geometry>
	<Route_Geometry aContract_Line_No="X140" aLBSL_Run_No="1" aSequence_No="66">
		<Direction>1</Direction>
		<Location_Easting>511138</Location_Easting>
		<Location_Northing>182213</Location_Northing>
		<Location_Longitude>-0.399276</Location_Longitude>
		<Location_Latitude>51.527902</Location_Latitude>
	</Route_Geometry>
	<Route_Geometry aContract_Line_No="X140" aLBSL_Run_No="1" aSequence_No="67">
		<Direction>1</Direction>
		<Location_Easting>511241</Location_Easting>
		<Location_Northing>182464</Location_Northing>
		<Location_Longitude>-0.397712</Location_Longitude>
		<Location_Latitude>51.530138</Location_Latitude>
	</Route_Geometry>
	<Route_Geometry aContract_Line_No="X140" aLBSL_Run_No="1" aSequence_No="68">
		<Direction>1</Direction>
		<Location_Easting>511291</Location_Easting>
		<Location_Northing>182653</Location_Northing>
		<Location_Longitude>-0.396932</Location_Longitude>
		<Location_Latitude>51.531827</Location_Latitude>
	</Route_Geometry>
	<Route_Geometry aContract_Line_No="X140" aLBSL_Run_No="1" aSequence_No="69">
		<Direction>1</Direction>
		<Location_Easting>511290</Location_Easting>
		<Location_Northing>182722</Location_Northing>
		<Location_Longitude>-0.396925</Location_Longitude>
		<Location_Latitude>51.532447</Location_Latitude>
	</Route_Geometry>
	<Route_Geometry aContract_Line_No="X140" aLBSL_Run_No="1" aSequence_No="70">
		<Direction>1</Direction>
		<Location_Easting>511306</Location_Easting>
		<Location_Northing>182820</Location_Northing>
		<Location_Longitude>-0.396663</Location_Longitude>
		<Location_Latitude>51.533325</Location_Latitude>
	</Route_Geometry>
	<Route_Geometry aContract_Line_No="X140" aLBSL_Run_No="1" aSequence_No="71">
		<Direction>1</Direction>
		<Location_Easting>511337</Location_Easting>
		<Location_Northing>182874</Location_Northing>
		<Location_Longitude>-0.396199</Location_Longitude>
		<Location_Latitude>51.533804</Location_Latitude>
	</Route_Geometry>
	<Route_Geometry aContract_Line_No="X140" aLBSL_Run_No="1" aSequence_No="72">
		<Direction>1</Direction>
		<Location_Easting>511527</Location_Easting>
		<Location_Northing>183069</Location_Northing>
		<Location_Longitude>-0.393399</Location_Longitude>
		<Location_Latitude>51.535519</Location_Latitude>
	</Route_Geometry>
	<Route_Geometry aContract_Line_No="X140" aLBSL_Run_No="1" aSequence_No="73">
		<Direction>1</Direction>
		<Location_Easting>511619</Location_Easting>
		<Location_Northing>183120</Location_Northing>
		<Location_Longitude>-0.392058</Location_Longitude>
		<Location_Latitude>51.535959</Location_Latitude>
	</Route_Geometry>
	<Route_Geometry aContract_Line_No="X140" aLBSL_Run_No="1" aSequence_No="74">
		<Direction>1</Direction>
		<Location_Easting>511672</Location_Easting>
		<Location_Northing>183138</Location_Northing>
		<Location_Longitude>-0.391288</Location_Longitude>
		<Location_Latitude>51.536111</Location_Latitude>
	</Route_Geometry>
	<Route_Geometry aContract_Line_No="X140" aLBSL_Run_No="1" aSequence_No="75">
		<Direction>1</Direction>
		<Location_Easting>511679</Location_Easting>
		<Location_Northing>183154</Location_Northing>
		<Location_Longitude>-0.391182</Location_Longitude>
		<Location_Latitude>51.536253</Location_Latitude>
	</Route_Geometry>
	<Route_Geometry aContract_Line_No="X140" aLBSL_Run_No="1" aSequence_No="76">
		<Direction>1</Direction>
		<Location_Easting>511702</Location_Easting>
		<Location_Northing>183169</Location_Northing>
		<Location_Longitude>-0.390846</Location_Longitude>
		<Location_Latitude>51.536383</Location_Latitude>
	</Route_Geometry>
	<Route_Geometry aContract_Line_No="X140" aLBSL_Run_No="1" aSequence_No="77">
		<Direction>1</Direction>
		<Location_Easting>511724</Location_Easting>
		<Location_Northing>183168</Location_Northing>
		<Location_Longitude>-0.390529</Location_Longitude>
		<Location_Latitude>51.536370</Location_Latitude>
	</Route_Geometry>
	<Route_Geometry aContract_Line_No="X140" aLBSL_Run_No="1" aSequence_No="78">
		<Direction>1</Direction>
		<Location_Easting>511940</Location_Easting>
		<Location_Northing>183406</Location_Northing>
		<Location_Longitude>-0.387340</Location_Longitude>
		<Location_Latitude>51.538466</Location_Latitude>
	</Route_Geometry>
	<Route_Geometry aContract_Line_No="X140" aLBSL_Run_No="1" aSequence_No="79">
		<Direction>1</Direction>
		<Location_Easting>512046</Location_Easting>
		<Location_Northing>183494</Location_Northing>
		<Location_Longitude>-0.385785</Location_Longitude>
		<Location_Latitude>51.539236</Location_Latitude>
	</Route_Geometry>
	<Route_Geometry aContract_Line_No="X140" aLBSL_Run_No="1" aSequence_No="80">
		<Direction>1</Direction>
		<Location_Easting>512140</Location_Easting>
		<Location_Northing>183548</Location_Northing>
		<Location_Longitude>-0.384412</Location_Longitude>
		<Location_Latitude>51.539703</Location_Latitude>
	</Route_Geometry>
	<Route_Geometry aContract_Line_No="X140" aLBSL_Run_No="1" aSequence_No="81">
		<Direction>1</Direction>
		<Location_Easting>512355</Location_Easting>
		<Location_Northing>183719</Location_Northing>
		<Location_Longitude>-0.381259</Location_Longitude>
		<Location_Latitude>51.541197</Location_Latitude>
	</Route_Geometry>
	<Route_Geometry aContract_Line_No="X140" aLBSL_Run_No="1" aSequence_No="82">
		<Direction>1</Direction>
		<Location_Easting>512500</Location_Easting>
		<Location_Northing>183855</Location_Northing>
		<Location_Longitude>-0.379126</Location_Longitude>
		<Location_Latitude>51.542391</Location_Latitude>
	</Route_Geometry>
	<Route_Geometry aContract_Line_No="X140" aLBSL_Run_No="1" aSequence_No="83">
		<Direction>1</Direction>
		<Location_Easting>512536</Location_Easting>
		<Location_Northing>183874</Location_Northing>
		<Location_Longitude>-0.378601</Location_Longitude>
		<Location_Latitude>51.542554</Location_Latitude>
	</Route_Geometry>
	<Route_Geometry aContract_Line_No="X140" aLBSL_Run_No="1" aSequence_No="84">
		<Direction>1</Direction>
		<Location_Easting>512547</Location_Easting>
		<Location_Northing>183893</Location_Northing>
		<Location_Longitude>-0.378436</Location_Longitude>
		<Location_Latitude>51.542723</Location_Latitude>
	</Route_Geometry>
	<Route_Geometry aContract_Line_No="X140" aLBSL_Run_No="1" aSequence_No="85">
		<Direction>1</Direction>
		<Location_Easting>512541</Location_Easting>
		<Location_Northing>183921</Location_Northing>
		<Location_Longitude>-0.378514</Location_Longitude>
		<Location_Latitude>51.542976</Location_Latitude>
	</Route_Geometry>
	<Route_Geometry aContract_Line_No="X140" aLBSL_Run_No="1" aSequence_No="86">
		<Direction>1</Direction>
		<Location_Easting>512568</Location_Easting>
		<Location_Northing>183956</Location_Northing>
		<Location_Longitude>-0.378113</Location_Longitude>
		<Location_Latitude>51.543285</Location_Latitude>
	</Route_Geometry>
	<Route_Geometry aContract_Line_No="X140" aLBSL_Run_No="1" aSequence_No="87">
		<Direction>1</Direction>
		<Location_Easting>512615</Location_Easting>
		<Location_Northing>183956</Location_Northing>
		<Location_Longitude>-0.377436</Location_Longitude>
		<Location_Latitude>51.543276</Location_Latitude>
	</Route_Geometry>
	<Route_Geometry aContract_Line_No="X140" aLBSL_Run_No="1" aSequence_No="88">
		<Direction>1</Direction>
		<Location_Easting>512845</Location_Easting>
		<Location_Northing>184065</Location_Northing>
		<Location_Longitude>-0.374086</Location_Longitude>
		<Location_Latitude>51.544209</Location_Latitude>
	</Route_Geometry>
	<Route_Geometry aContract_Line_No="X140" aLBSL_Run_No="1" aSequence_No="89">
		<Direction>1</Direction>
		<Location_Easting>513000</Location_Easting>
		<Location_Northing>184199</Location_Northing>
		<Location_Longitude>-0.371808</Location_Longitude>
		<Location_Latitude>51.545383</Location_Latitude>
	</Route_Geometry>
	<Route_Geometry aContract_Line_No="X140" aLBSL_Run_No="1" aSequence_No="90">
		<Direction>1</Direction>
		<Location_Easting>513299</Location_Easting>
		<Location_Northing>184568</Location_Northing>
		<Location_Longitude>-0.367380</Location_Longitude>
		<Location_Latitude>51.548639</Location_Latitude>
	</Route_Geometry>
	<Route_Geometry aContract_Line_No="X140" aLBSL_Run_No="1" aSequence_No="91">
		<Direction>1</Direction>
		<Location_Easting>513347</Location_Easting>
		<Location_Northing>184610</Location_Northing>
		<Location_Longitude>-0.366674</Location_Longitude>
		<Location_Latitude>51.549007</Location_Latitude>
	</Route_Geometry>
	<Route_Geometry aContract_Line_No="X140" aLBSL_Run_No="1" aSequence_No="92">
		<Direction>1</Direction>
		<Location_Easting>513678</Location_Easting>
		<Location_Northing>184808</Location_Northing>
		<Location_Longitude>-0.361838</Location_Longitude>
		<Location_Latitude>51.550720</Location_Latitude>
	</Route_Geometry>
	<Route_Geometry aContract_Line_No="X140" aLBSL_Run_No="1" aSequence_No="93">
		<Direction>1</Direction>
		<Location_Easting>513736</Location_Easting>
		<Location_Northing>184862</Location_Northing>
		<Location_Longitude>-0.360985</Location_Longitude>
		<Location_Latitude>51.551194</Location_Latitude>
	</Route_Geometry>
	<Route_Geometry aContract_Line_No="X140" aLBSL_Run_No="1" aSequence_No="94">
		<Direction>1</Direction>
		<Location_Easting>513763</Location_Easting>
		<Location_Northing>184900</Location_Northing>
		<Location_Longitude>-0.360583</Location_Longitude>
		<Location_Latitude>51.551530</Location_Latitude>
	</Route_Geometry>
	<Route_Geometry aContract_Line_No="X140" aLBSL_Run_No="1" aSequence_No="95">
		<Direction>1</Direction>
		<Location_Easting>513786</Location_Easting>
		<Location_Northing>184989</Location_Northing>
		<Location_Longitude>-0.360223</Location_Longitude>
		<Location_Latitude>51.552325</Location_Latitude>
	</Route_Geometry>
	<Route_Geometry aContract_Line_No="X140" aLBSL_Run_No="1" aSequence_No="96">
		<Direction>1</Direction>
		<Location_Easting>513790</Location_Easting>
		<Location_Northing>185256</Location_Northing>
		<Location_Longitude>-0.360079</Location_Longitude>
		<Location_Latitude>51.554724</Location_Latitude>
	</Route_Geometry>
	<Route_Geometry aContract_Line_No="X140" aLBSL_Run_No="1" aSequence_No="97">
		<Direction>1</Direction>
		<Location_Easting>513782</Location_Easting>
		<Location_Northing>185296</Location_Northing>
		<Location_Longitude>-0.360182</Location_Longitude>
		<Location_Latitude>51.555086</Location_Latitude>
	</Route_Geometry>
	<Route_Geometry aContract_Line_No="X140" aLBSL_Run_No="1" aSequence_No="98">
		<Direction>1</Direction>
		<Location_Easting>513753</Location_Easting>
		<Location_Northing>185335</Location_Northing>
		<Location_Longitude>-0.360587</Location_Longitude>
		<Location_Latitude>51.555442</Location_Latitude>
	</Route_Geometry>
	<Route_Geometry aContract_Line_No="X140" aLBSL_Run_No="1" aSequence_No="99">
		<Direction>1</Direction>
		<Location_Easting>513675</Location_Easting>
		<Location_Northing>185409</Location_Northing>
		<Location_Longitude>-0.361688</Location_Longitude>
		<Location_Latitude>51.556123</Location_Latitude>
	</Route_Geometry>
	<Route_Geometry aContract_Line_No="X140" aLBSL_Run_No="1" aSequence_No="100">
		<Direction>1</Direction>
		<Location_Easting>513655</Location_Easting>
		<Location_Northing>185447</Location_Northing>
		<Location_Longitude>-0.361964</Location_Longitude>
		<Location_Latitude>51.556468</Location_Latitude>
	</Route_Geometry>
	<Route_Geometry aContract_Line_No="X140" aLBSL_Run_No="1" aSequence_No="101">
		<Direction>1</Direction>
		<Location_Easting>513633</Location_Easting>
		<Location_Northing>185526</Location_Northing>
		<Location_Longitude>-0.362256</Location_Longitude>
		<Location_Latitude>51.557183</Location_Latitude>
	</Route_Geometry>
	<Route_Geometry aContract_Line_No="X140" aLBSL_Run_No="1" aSequence_No="102">
		<Direction>1</Direction>
		<Location_Easting>513823</Location_Easting>
		<Location_Northing>185785</Location_Northing>
		<Location_Longitude>-0.359432</Location_Longitude>
		<Location_Latitude>51.559472</Location_Latitude>
	</Route_Geometry>
	<Route_Geometry aContract_Line_No="X140" aLBSL_Run_No="1" aSequence_No="103">
		<Direction>1</Direction>
		<Location_Easting>514133</Location_Easting>
		<Location_Northing>186256</Location_Northing>
		<Location_Longitude>-0.354810</Location_Longitude>
		<Location_Latitude>51.563643</Location_Latitude>
	</Route_Geometry>
	<Route_Geometry aContract_Line_No="X140" aLBSL_Run_No="1" aSequence_No="104">
		<Direction>1</Direction>
		<Location_Easting>514211</Location_Easting>
		<Location_Northing>186348</Location_Northing>
		<Location_Longitude>-0.353655</Location_Longitude>
		<Location_Latitude>51.564454</Location_Latitude>
	</Route_Geometry>
	<Route_Geometry aContract_Line_No="X140" aLBSL_Run_No="1" aSequence_No="105">
		<Direction>1</Direction>
		<Location_Easting>514276</Location_Easting>
		<Location_Northing>186397</Location_Northing>
		<Location_Longitude>-0.352702</Location_Longitude>
		<Location_Latitude>51.564881</Location_Latitude>
	</Route_Geometry>
	<Route_Geometry aContract_Line_No="X140" aLBSL_Run_No="1" aSequence_No="106">
		<Direction>1</Direction>
		<Location_Easting>514450</Location_Easting>
		<Location_Northing>186633</Location_Northing>
		<Location_Longitude>-0.350116</Location_Longitude>
		<Location_Latitude>51.566967</Location_Latitude>
	</Route_Geometry>
	<Route_Geometry aContract_Line_No="X140" aLBSL_Run_No="1" aSequence_No="107">
		<Direction>1</Direction>
		<Location_Easting>514442</Location_Easting>
		<Location_Northing>186642</Location_Northing>
		<Location_Longitude>-0.350228</Location_Longitude>
		<Location_Latitude>51.567050</Location_Latitude>
	</Route_Geometry>
	<Route_Geometry aContract_Line_No="X140" aLBSL_Run_No="1" aSequence_No="108">
		<Direction>1</Direction>
		<Location_Easting>514457</Location_Easting>
		<Location_Northing>186647</Location_Northing>
		<Location_Longitude>-0.350010</Location_Longitude>
		<Location_Latitude>51.567092</Location_Latitude>
	</Route_Geometry>
	<Route_Geometry aContract_Line_No="X140" aLBSL_Run_No="1" aSequence_No="109">
		<Direction>1</Direction>
		<Location_Easting>514644</Location_Easting>
		<Location_Northing>186866</Location_Northing>
		<Location_Longitude>-0.347242</Location_Longitude>
		<Location_Latitude>51.569022</Location_Latitude>
	</Route_Geometry>
	<Route_Geometry aContract_Line_No="X140" aLBSL_Run_No="1" aSequence_No="110">
		<Direction>1</Direction>
		<Location_Easting>514808</Location_Easting>
		<Location_Northing>187272</Location_Northing>
		<Location_Longitude>-0.344744</Location_Longitude>
		<Location_Latitude>51.572638</Location_Latitude>
	</Route_Geometry>
	<Route_Geometry aContract_Line_No="X140" aLBSL_Run_No="1" aSequence_No="111">
		<Direction>1</Direction>
		<Location_Easting>514859</Location_Easting>
		<Location_Northing>187333</Location_Northing>
		<Location_Longitude>-0.343988</Location_Longitude>
		<Location_Latitude>51.573176</Location_Latitude>
	</Route_Geometry>
	<Route_Geometry aContract_Line_No="X140" aLBSL_Run_No="1" aSequence_No="112">
		<Direction>1</Direction>
		<Location_Easting>514925</Location_Easting>
		<Location_Northing>187709</Location_Northing>
		<Location_Longitude>-0.342914</Location_Longitude>
		<Location_Latitude>51.576541</Location_Latitude>
	</Route_Geometry>
	<Route_Geometry aContract_Line_No="X140" aLBSL_Run_No="1" aSequence_No="113">
		<Direction>1</Direction>
		<Location_Easting>514920</Location_Easting>
		<Location_Northing>187787</Location_Northing>
		<Location_Longitude>-0.342960</Location_Longitude>
		<Location_Latitude>51.577244</Location_Latitude>
	</Route_Geometry>
	<Route_Geometry aContract_Line_No="X140" aLBSL_Run_No="1" aSequence_No="114">
		<Direction>1</Direction>
		<Location_Easting>514941</Location_Easting>
		<Location_Northing>187879</Location_Northing>
		<Location_Longitude>-0.342627</Location_Longitude>
		<Location_Latitude>51.578066</Location_Latitude>
	</Route_Geometry>
	<Route_Geometry aContract_Line_No="X140" aLBSL_Run_No="1" aSequence_No="115">
		<Direction>1</Direction>
		<Location_Easting>514946</Location_Easting>
		<Location_Northing>187957</Location_Northing>
		<Location_Longitude>-0.342529</Location_Longitude>
		<Location_Latitude>51.578766</Location_Latitude>
	</Route_Geometry>
	<Route_Geometry aContract_Line_No="X140" aLBSL_Run_No="1" aSequence_No="116">
		<Direction>1</Direction>
		<Location_Easting>514979</Location_Easting>
		<Location_Northing>188053</Location_Northing>
		<Location_Longitude>-0.342022</Location_Longitude>
		<Location_Latitude>51.579622</Location_Latitude>
	</Route_Geometry>
	<Route_Geometry aContract_Line_No="X140" aLBSL_Run_No="1" aSequence_No="117">
		<Direction>1</Direction>
		<Location_Easting>514982</Location_Easting>
		<Location_Northing>188115</Location_Northing>
		<Location_Longitude>-0.341958</Location_Longitude>
		<Location_Latitude>51.580179</Location_Latitude>
	</Route_Geometry>
	<Route_Geometry aContract_Line_No="X140" aLBSL_Run_No="1" aSequence_No="118">
		<Direction>1</Direction>
		<Location_Easting>514964</Location_Easting>
		<Location_Northing>188170</Location_Northing>
		<Location_Longitude>-0.342200</Location_Longitude>
		<Location_Latitude>51.580677</Location_Latitude>
	</Route_Geometry>
	<Route_Geometry aContract_Line_No="X140" aLBSL_Run_No="1" aSequence_No="119">
		<Direction>1</Direction>
		<Location_Easting>514983</Location_Easting>
		<Location_Northing>188179</Location_Northing>
		<Location_Longitude>-0.341923</Location_Longitude>
		<Location_Latitude>51.580754</Location_Latitude>
	</Route_Geometry>
	<Route_Geometry aContract_Line_No="X140" aLBSL_Run_No="1" aSequence_No="120">
		<Direction>1</Direction>
		<Location_Easting>514997</Location_Easting>
		<Location_Northing>188164</Location_Northing>
		<Location_Longitude>-0.341726</Location_Longitude>
		<Location_Latitude>51.580616</Location_Latitude>
	</Route_Geometry>
	<Route_Geometry aContract_Line_No="X140" aLBSL_Run_No="1" aSequence_No="121">
		<Direction>1</Direction>
		<Location_Easting>514992</Location_Easting>
		<Location_Northing>188124</Location_Northing>
		<Location_Longitude>-0.341811</Location_Longitude>
		<Location_Latitude>51.580258</Location_Latitude>
	</Route_Geometry>
	<Route_Geometry aContract_Line_No="X140" aLBSL_Run_No="1" aSequence_No="122">
		<Direction>1</Direction>
		<Location_Easting>515005</Location_Easting>
		<Location_Northing>188101</Location_Northing>
		<Location_Longitude>-0.341631</Location_Longitude>
		<Location_Latitude>51.580048</Location_Latitude>
	</Route_Geometry>
	<Route_Geometry aContract_Line_No="X140" aLBSL_Run_No="1" aSequence_No="123">
		<Direction>1</Direction>
		<Location_Easting>515090</Location_Easting>
		<Location_Northing>188092</Location_Northing>
		<Location_Longitude>-0.340408</Location_Longitude>
		<Location_Latitude>51.579950</Location_Latitude>
	</Route_Geometry>
	<Route_Geometry aContract_Line_No="X140" aLBSL_Run_No="1" aSequence_No="124">
		<Direction>1</Direction>
		<Location_Easting>515084</Location_Easting>
		<Location_Northing>188193</Location_Northing>
		<Location_Longitude>-0.340461</Location_Longitude>
		<Location_Latitude>51.580859</Location_Latitude>
	</Route_Geometry>
	<Route_Geometry aContract_Line_No="X140" aLBSL_Run_No="1" aSequence_No="125">
		<Direction>1</Direction>
		<Location_Easting>515198</Location_Easting>
		<Location_Northing>188218</Location_Northing>
		<Location_Longitude>-0.338809</Location_Longitude>
		<Location_Latitude>51.581061</Location_Latitude>
	</Route_Geometry>
	<Route_Geometry aContract_Line_No="X140" aLBSL_Run_No="1" aSequence_No="126">
		<Direction>1</Direction>
		<Location_Easting>515228</Location_Easting>
		<Location_Northing>188202</Location_Northing>
		<Location_Longitude>-0.338381</Location_Longitude>
		<Location_Latitude>51.580911</Location_Latitude>
	</Route_Geometry>
	<Route_Geometry aContract_Line_No="X140" aLBSL_Run_No="1" aSequence_No="127">
		<Direction>1</Direction>
		<Location_Easting>515233</Location_Easting>
		<Location_Northing>188106</Location_Northing>
		<Location_Longitude>-0.338341</Location_Longitude>
		<Location_Latitude>51.580047</Location_Latitude>
	</Route_Geometry>
	<Route_Geometry aContract_Line_No="X140" aLBSL_Run_No="1" aSequence_No="128">
		<Direction>1</Direction>
		<Location_Easting>515242</Location_Easting>
		<Location_Northing>188093</Location_Northing>
		<Location_Longitude>-0.338215</Location_Longitude>
		<Location_Latitude>51.579928</Location_Latitude>
	</Route_Geometry>
	<Route_Geometry aContract_Line_No="X140" aLBSL_Run_No="1" aSequence_No="129">
		<Direction>1</Direction>
		<Location_Easting>515251</Location_Easting>
		<Location_Northing>188092</Location_Northing>
		<Location_Longitude>-0.338086</Location_Longitude>
		<Location_Latitude>51.579917</Location_Latitude>
	</Route_Geometry>
	<Route_Geometry aContract_Line_No="X140" aLBSL_Run_No="1" aSequence_No="130">
		<Direction>1</Direction>
		<Location_Easting>515272</Location_Easting>
		<Location_Northing>188092</Location_Northing>
		<Location_Longitude>-0.337782</Location_Longitude>
		<Location_Latitude>51.579913</Location_Latitude>
	</Route_Geometry>
	<Route_Geometry aContract_Line_No="X140" aLBSL_Run_No="2" aSequence_No="1">
		<Direction>2</Direction>
		<Location_Easting>515331</Location_Easting>
		<Location_Northing>188114</Location_Northing>
		<Location_Longitude>-0.336924</Location_Longitude>
		<Location_Latitude>51.580099</Location_Latitude>
	</Route_Geometry>
	<Route_Geometry aContract_Line_No="X140" aLBSL_Run_No="2" aSequence_No="2">
		<Direction>2</Direction>
		<Location_Easting>515285</Location_Easting>
		<Location_Northing>188115</Location_Northing>
		<Location_Longitude>-0.337587</Location_Longitude>
		<Location_Latitude>51.580117</Location_Latitude>
	</Route_Geometry>
	<Route_Geometry aContract_Line_No="X140" aLBSL_Run_No="2" aSequence_No="3">
		<Direction>2</Direction>
		<Location_Easting>515259</Location_Easting>
		<Location_Northing>188115</Location_Northing>
		<Location_Longitude>-0.337963</Location_Longitude>
		<Location_Latitude>51.580123</Location_Latitude>
	</Route_Geometry>
	<Route_Geometry aContract_Line_No="X140" aLBSL_Run_No="2" aSequence_No="4">
		<Direction>2</Direction>
		<Location_Easting>515115</Location_Easting>
		<Location_Northing>188093</Location_Northing>
		<Location_Longitude>-0.340047</Location_Longitude>
		<Location_Latitude>51.579954</Location_Latitude>
	</Route_Geometry>
	<Route_Geometry aContract_Line_No="X140" aLBSL_Run_No="2" aSequence_No="5">
		<Direction>2</Direction>
		<Location_Easting>514995</Location_Easting>
		<Location_Northing>188093</Location_Northing>
		<Location_Longitude>-0.341778</Location_Longitude>
		<Location_Latitude>51.579979</Location_Latitude>
	</Route_Geometry>
	<Route_Geometry aContract_Line_No="X140" aLBSL_Run_No="2" aSequence_No="6">
		<Direction>2</Direction>
		<Location_Easting>514988</Location_Easting>
		<Location_Northing>188082</Location_Northing>
		<Location_Longitude>-0.341883</Location_Longitude>
		<Location_Latitude>51.579881</Location_Latitude>
	</Route_Geometry>
	<Route_Geometry aContract_Line_No="X140" aLBSL_Run_No="2" aSequence_No="7">
		<Direction>2</Direction>
		<Location_Easting>514998</Location_Easting>
		<Location_Northing>188029</Location_Northing>
		<Location_Longitude>-0.341756</Location_Longitude>
		<Location_Latitude>51.579403</Location_Latitude>
	</Route_Geometry>
	<Route_Geometry aContract_Line_No="X140" aLBSL_Run_No="2" aSequence_No="8">
		<Direction>2</Direction>
		<Location_Easting>514963</Location_Easting>
		<Location_Northing>187996</Location_Northing>
		<Location_Longitude>-0.342271</Location_Longitude>
		<Location_Latitude>51.579113</Location_Latitude>
	</Route_Geometry>
	<Route_Geometry aContract_Line_No="X140" aLBSL_Run_No="2" aSequence_No="9">
		<Direction>2</Direction>
		<Location_Easting>514946</Location_Easting>
		<Location_Northing>187957</Location_Northing>
		<Location_Longitude>-0.342529</Location_Longitude>
		<Location_Latitude>51.578766</Location_Latitude>
	</Route_Geometry>
	<Route_Geometry aContract_Line_No="X140" aLBSL_Run_No="2" aSequence_No="10">
		<Direction>2</Direction>
		<Location_Easting>514941</Location_Easting>
		<Location_Northing>187879</Location_Northing>
		<Location_Longitude>-0.342627</Location_Longitude>
		<Location_Latitude>51.578066</Location_Latitude>
	</Route_Geometry>
	<Route_Geometry aContract_Line_No="X140" aLBSL_Run_No="2" aSequence_No="11">
		<Direction>2</Direction>
		<Location_Easting>514920</Location_Easting>
		<Location_Northing>187787</Location_Northing>
		<Location_Longitude>-0.342960</Location_Longitude>
		<Location_Latitude>51.577244</Location_Latitude>
	</Route_Geometry>
	<Route_Geometry aContract_Line_No="X140" aLBSL_Run_No="2" aSequence_No="12">
		<Direction>2</Direction>
		<Location_Easting>514925</Location_Easting>
		<Location_Northing>187709</Location_Northing>
		<Location_Longitude>-0.342914</Location_Longitude>
		<Location_Latitude>51.576541</Location_Latitude>
	</Route_Geometry>
	<Route_Geometry aContract_Line_No="X140" aLBSL_Run_No="2" aSequence_No="13">
		<Direction>2</Direction>
		<Location_Easting>514889</Location_Easting>
		<Location_Northing>187517</Location_Northing>
		<Location_Longitude>-0.343496</Location_Longitude>
		<Location_Latitude>51.574823</Location_Latitude>
	</Route_Geometry>
	<Route_Geometry aContract_Line_No="X140" aLBSL_Run_No="2" aSequence_No="14">
		<Direction>2</Direction>
		<Location_Easting>514880</Location_Easting>
		<Location_Northing>187425</Location_Northing>
		<Location_Longitude>-0.343656</Location_Longitude>
		<Location_Latitude>51.573998</Location_Latitude>
	</Route_Geometry>
	<Route_Geometry aContract_Line_No="X140" aLBSL_Run_No="2" aSequence_No="15">
		<Direction>2</Direction>
		<Location_Easting>514859</Location_Easting>
		<Location_Northing>187333</Location_Northing>
		<Location_Longitude>-0.343988</Location_Longitude>
		<Location_Latitude>51.573176</Location_Latitude>
	</Route_Geometry>
	<Route_Geometry aContract_Line_No="X140" aLBSL_Run_No="2" aSequence_No="16">
		<Direction>2</Direction>
		<Location_Easting>514845</Location_Easting>
		<Location_Northing>187306</Location_Northing>
		<Location_Longitude>-0.344199</Location_Longitude>
		<Location_Latitude>51.572936</Location_Latitude>
	</Route_Geometry>
	<Route_Geometry aContract_Line_No="X140" aLBSL_Run_No="2" aSequence_No="17">
		<Direction>2</Direction>
		<Location_Easting>514808</Location_Easting>
		<Location_Northing>187272</Location_Northing>
		<Location_Longitude>-0.344744</Location_Longitude>
		<Location_Latitude>51.572638</Location_Latitude>
	</Route_Geometry>
	<Route_Geometry aContract_Line_No="X140" aLBSL_Run_No="2" aSequence_No="18">
		<Direction>2</Direction>
		<Location_Easting>514672</Location_Easting>
		<Location_Northing>186928</Location_Northing>
		<Location_Longitude>-0.346818</Location_Longitude>
		<Location_Latitude>51.569574</Location_Latitude>
	</Route_Geometry>
	<Route_Geometry aContract_Line_No="X140" aLBSL_Run_No="2" aSequence_No="19">
		<Direction>2</Direction>
		<Location_Easting>514678</Location_Easting>
		<Location_Northing>186900</Location_Northing>
		<Location_Longitude>-0.346740</Location_Longitude>
		<Location_Latitude>51.569321</Location_Latitude>
	</Route_Geometry>
	<Route_Geometry aContract_Line_No="X140" aLBSL_Run_No="2" aSequence_No="20">
		<Direction>2</Direction>
		<Location_Easting>514457</Location_Easting>
		<Location_Northing>186647</Location_Northing>
		<Location_Longitude>-0.350010</Location_Longitude>
		<Location_Latitude>51.567092</Location_Latitude>
	</Route_Geometry>
	<Route_Geometry aContract_Line_No="X140" aLBSL_Run_No="2" aSequence_No="21">
		<Direction>2</Direction>
		<Location_Easting>514460</Location_Easting>
		<Location_Northing>186640</Location_Northing>
		<Location_Longitude>-0.349969</Location_Longitude>
		<Location_Latitude>51.567028</Location_Latitude>
	</Route_Geometry>
	<Route_Geometry aContract_Line_No="X140" aLBSL_Run_No="2" aSequence_No="22">
		<Direction>2</Direction>
		<Location_Easting>514276</Location_Easting>
		<Location_Northing>186397</Location_Northing>
		<Location_Longitude>-0.352702</Location_Longitude>
		<Location_Latitude>51.564881</Location_Latitude>
	</Route_Geometry>
	<Route_Geometry aContract_Line_No="X140" aLBSL_Run_No="2" aSequence_No="23">
		<Direction>2</Direction>
		<Location_Easting>514211</Location_Easting>
		<Location_Northing>186348</Location_Northing>
		<Location_Longitude>-0.353655</Location_Longitude>
		<Location_Latitude>51.564454</Location_Latitude>
	</Route_Geometry>
	<Route_Geometry aContract_Line_No="X140" aLBSL_Run_No="2" aSequence_No="24">
		<Direction>2</Direction>
		<Location_Easting>514133</Location_Easting>
		<Location_Northing>186256</Location_Northing>
		<Location_Longitude>-0.354810</Location_Longitude>
		<Location_Latitude>51.563643</Location_Latitude>
	</Route_Geometry>
	<Route_Geometry aContract_Line_No="X140" aLBSL_Run_No="2" aSequence_No="25">
		<Direction>2</Direction>
		<Location_Easting>513823</Location_Easting>
		<Location_Northing>185785</Location_Northing>
		<Location_Longitude>-0.359432</Location_Longitude>
		<Location_Latitude>51.559472</Location_Latitude>
	</Route_Geometry>
	<Route_Geometry aContract_Line_No="X140" aLBSL_Run_No="2" aSequence_No="26">
		<Direction>2</Direction>
		<Location_Easting>513633</Location_Easting>
		<Location_Northing>185526</Location_Northing>
		<Location_Longitude>-0.362256</Location_Longitude>
		<Location_Latitude>51.557183</Location_Latitude>
	</Route_Geometry>
	<Route_Geometry aContract_Line_No="X140" aLBSL_Run_No="2" aSequence_No="27">
		<Direction>2</Direction>
		<Location_Easting>513655</Location_Easting>
		<Location_Northing>185447</Location_Northing>
		<Location_Longitude>-0.361964</Location_Longitude>
		<Location_Latitude>51.556468</Location_Latitude>
	</Route_Geometry>
	<Route_Geometry aContract_Line_No="X140" aLBSL_Run_No="2" aSequence_No="28">
		<Direction>2</Direction>
		<Location_Easting>513675</Location_Easting>
		<Location_Northing>185409</Location_Northing>
		<Location_Longitude>-0.361688</Location_Longitude>
		<Location_Latitude>51.556123</Location_Latitude>
	</Route_Geometry>
	<Route_Geometry aContract_Line_No="X140" aLBSL_Run_No="2" aSequence_No="29">
		<Direction>2</Direction>
		<Location_Easting>513757</Location_Easting>
		<Location_Northing>185330</Location_Northing>
		<Location_Longitude>-0.360531</Location_Longitude>
		<Location_Latitude>51.555396</Location_Latitude>
	</Route_Geometry>
	<Route_Geometry aContract_Line_No="X140" aLBSL_Run_No="2" aSequence_No="30">
		<Direction>2</Direction>
		<Location_Easting>513791</Location_Easting>
		<Location_Northing>185321</Location_Northing>
		<Location_Longitude>-0.360044</Location_Longitude>
		<Location_Latitude>51.555308</Location_Latitude>
	</Route_Geometry>
	<Route_Geometry aContract_Line_No="X140" aLBSL_Run_No="2" aSequence_No="31">
		<Direction>2</Direction>
		<Location_Easting>513812</Location_Easting>
		<Location_Northing>185328</Location_Northing>
		<Location_Longitude>-0.359739</Location_Longitude>
		<Location_Latitude>51.555367</Location_Latitude>
	</Route_Geometry>
	<Route_Geometry aContract_Line_No="X140" aLBSL_Run_No="2" aSequence_No="32">
		<Direction>2</Direction>
		<Location_Easting>513834</Location_Easting>
		<Location_Northing>185314</Location_Northing>
		<Location_Longitude>-0.359426</Location_Longitude>
		<Location_Latitude>51.555237</Location_Latitude>
	</Route_Geometry>
	<Route_Geometry aContract_Line_No="X140" aLBSL_Run_No="2" aSequence_No="33">
		<Direction>2</Direction>
		<Location_Easting>513828</Location_Easting>
		<Location_Northing>185280</Location_Northing>
		<Location_Longitude>-0.359524</Location_Longitude>
		<Location_Latitude>51.554932</Location_Latitude>
	</Route_Geometry>
	<Route_Geometry aContract_Line_No="X140" aLBSL_Run_No="2" aSequence_No="34">
		<Direction>2</Direction>
		<Location_Easting>513803</Location_Easting>
		<Location_Northing>185274</Location_Northing>
		<Location_Longitude>-0.359886</Location_Longitude>
		<Location_Latitude>51.554883</Location_Latitude>
	</Route_Geometry>
	<Route_Geometry aContract_Line_No="X140" aLBSL_Run_No="2" aSequence_No="35">
		<Direction>2</Direction>
		<Location_Easting>513790</Location_Easting>
		<Location_Northing>185256</Location_Northing>
		<Location_Longitude>-0.360079</Location_Longitude>
		<Location_Latitude>51.554724</Location_Latitude>
	</Route_Geometry>
	<Route_Geometry aContract_Line_No="X140" aLBSL_Run_No="2" aSequence_No="36">
		<Direction>2</Direction>
		<Location_Easting>513786</Location_Easting>
		<Location_Northing>184989</Location_Northing>
		<Location_Longitude>-0.360223</Location_Longitude>
		<Location_Latitude>51.552325</Location_Latitude>
	</Route_Geometry>
	<Route_Geometry aContract_Line_No="X140" aLBSL_Run_No="2" aSequence_No="37">
		<Direction>2</Direction>
		<Location_Easting>513763</Location_Easting>
		<Location_Northing>184900</Location_Northing>
		<Location_Longitude>-0.360583</Location_Longitude>
		<Location_Latitude>51.551530</Location_Latitude>
	</Route_Geometry>
	<Route_Geometry aContract_Line_No="X140" aLBSL_Run_No="2" aSequence_No="38">
		<Direction>2</Direction>
		<Location_Easting>513736</Location_Easting>
		<Location_Northing>184862</Location_Northing>
		<Location_Longitude>-0.360985</Location_Longitude>
		<Location_Latitude>51.551194</Location_Latitude>
	</Route_Geometry>
	<Route_Geometry aContract_Line_No="X140" aLBSL_Run_No="2" aSequence_No="39">
		<Direction>2</Direction>
		<Location_Easting>513678</Location_Easting>
		<Location_Northing>184808</Location_Northing>
		<Location_Longitude>-0.361838</Location_Longitude>
		<Location_Latitude>51.550720</Location_Latitude>
	</Route_Geometry>
	<Route_Geometry aContract_Line_No="X140" aLBSL_Run_No="2" aSequence_No="40">
		<Direction>2</Direction>
		<Location_Easting>513347</Location_Easting>
		<Location_Northing>184610</Location_Northing>
		<Location_Longitude>-0.366674</Location_Longitude>
		<Location_Latitude>51.549007</Location_Latitude>
	</Route_Geometry>
	<Route_Geometry aContract_Line_No="X140" aLBSL_Run_No="2" aSequence_No="41">
		<Direction>2</Direction>
		<Location_Easting>513308</Location_Easting>
		<Location_Northing>184573</Location_Northing>
		<Location_Longitude>-0.367248</Location_Longitude>
		<Location_Latitude>51.548682</Location_Latitude>
	</Route_Geometry>
	<Route_Geometry aContract_Line_No="X140" aLBSL_Run_No="2" aSequence_No="42">
		<Direction>2</Direction>
		<Location_Easting>513000</Location_Easting>
		<Location_Northing>184199</Location_Northing>
		<Location_Longitude>-0.371808</Location_Longitude>
		<Location_Latitude>51.545383</Location_Latitude>
	</Route_Geometry>
	<Route_Geometry aContract_Line_No="X140" aLBSL_Run_No="2" aSequence_No="43">
		<Direction>2</Direction>
		<Location_Easting>512845</Location_Easting>
		<Location_Northing>184065</Location_Northing>
		<Location_Longitude>-0.374086</Location_Longitude>
		<Location_Latitude>51.544209</Location_Latitude>
	</Route_Geometry>
	<Route_Geometry aContract_Line_No="X140" aLBSL_Run_No="2" aSequence_No="44">
		<Direction>2</Direction>
		<Location_Easting>512650</Location_Easting>
		<Location_Northing>183970</Location_Northing>
		<Location_Longitude>-0.376927</Location_Longitude>
		<Location_Latitude>51.543394</Location_Latitude>
	</Route_Geometry>
	<Route_Geometry aContract_Line_No="X140" aLBSL_Run_No="2" aSequence_No="45">
		<Direction>2</Direction>
		<Location_Easting>512636</Location_Easting>
		<Location_Northing>183941</Location_Northing>
		<Location_Longitude>-0.377138</Location_Longitude>
		<Location_Latitude>51.543137</Location_Latitude>
	</Route_Geometry>
	<Route_Geometry aContract_Line_No="X140" aLBSL_Run_No="2" aSequence_No="46">
		<Direction>2</Direction>
		<Location_Easting>512645</Location_Easting>
		<Location_Northing>183915</Location_Northing>
		<Location_Longitude>-0.377017</Location_Longitude>
		<Location_Latitude>51.542901</Location_Latitude>
	</Route_Geometry>
	<Route_Geometry aContract_Line_No="X140" aLBSL_Run_No="2" aSequence_No="47">
		<Direction>2</Direction>
		<Location_Easting>512641</Location_Easting>
		<Location_Northing>183891</Location_Northing>
		<Location_Longitude>-0.377082</Location_Longitude>
		<Location_Latitude>51.542686</Location_Latitude>
	</Route_Geometry>
	<Route_Geometry aContract_Line_No="X140" aLBSL_Run_No="2" aSequence_No="48">
		<Direction>2</Direction>
		<Location_Easting>512614</Location_Easting>
		<Location_Northing>183871</Location_Northing>
		<Location_Longitude>-0.377478</Location_Longitude>
		<Location_Latitude>51.542512</Location_Latitude>
	</Route_Geometry>
	<Route_Geometry aContract_Line_No="X140" aLBSL_Run_No="2" aSequence_No="49">
		<Direction>2</Direction>
		<Location_Easting>512523</Location_Easting>
		<Location_Northing>183855</Location_Northing>
		<Location_Longitude>-0.378794</Location_Longitude>
		<Location_Latitude>51.542386</Location_Latitude>
	</Route_Geometry>
	<Route_Geometry aContract_Line_No="X140" aLBSL_Run_No="2" aSequence_No="50">
		<Direction>2</Direction>
		<Location_Easting>512488</Location_Easting>
		<Location_Northing>183837</Location_Northing>
		<Location_Longitude>-0.379304</Location_Longitude>
		<Location_Latitude>51.542231</Location_Latitude>
	</Route_Geometry>
	<Route_Geometry aContract_Line_No="X140" aLBSL_Run_No="2" aSequence_No="51">
		<Direction>2</Direction>
		<Location_Easting>512387</Location_Easting>
		<Location_Northing>183739</Location_Northing>
		<Location_Longitude>-0.380792</Location_Longitude>
		<Location_Latitude>51.541371</Location_Latitude>
	</Route_Geometry>
	<Route_Geometry aContract_Line_No="X140" aLBSL_Run_No="2" aSequence_No="52">
		<Direction>2</Direction>
		<Location_Easting>512128</Location_Easting>
		<Location_Northing>183528</Location_Northing>
		<Location_Longitude>-0.384592</Location_Longitude>
		<Location_Latitude>51.539526</Location_Latitude>
	</Route_Geometry>
	<Route_Geometry aContract_Line_No="X140" aLBSL_Run_No="2" aSequence_No="53">
		<Direction>2</Direction>
		<Location_Easting>512051</Location_Easting>
		<Location_Northing>183488</Location_Northing>
		<Location_Longitude>-0.385714</Location_Longitude>
		<Location_Latitude>51.539181</Location_Latitude>
	</Route_Geometry>
	<Route_Geometry aContract_Line_No="X140" aLBSL_Run_No="2" aSequence_No="54">
		<Direction>2</Direction>
		<Location_Easting>511948</Location_Easting>
		<Location_Northing>183403</Location_Northing>
		<Location_Longitude>-0.387226</Location_Longitude>
		<Location_Latitude>51.538438</Location_Latitude>
	</Route_Geometry>
	<Route_Geometry aContract_Line_No="X140" aLBSL_Run_No="2" aSequence_No="55">
		<Direction>2</Direction>
		<Location_Easting>511772</Location_Easting>
		<Location_Northing>183205</Location_Northing>
		<Location_Longitude>-0.389826</Location_Longitude>
		<Location_Latitude>51.536693</Location_Latitude>
	</Route_Geometry>
	<Route_Geometry aContract_Line_No="X140" aLBSL_Run_No="2" aSequence_No="56">
		<Direction>2</Direction>
		<Location_Easting>511746</Location_Easting>
		<Location_Northing>183152</Location_Northing>
		<Location_Longitude>-0.390217</Location_Longitude>
		<Location_Latitude>51.536222</Location_Latitude>
	</Route_Geometry>
	<Route_Geometry aContract_Line_No="X140" aLBSL_Run_No="2" aSequence_No="57">
		<Direction>2</Direction>
		<Location_Easting>511753</Location_Easting>
		<Location_Northing>183123</Location_Northing>
		<Location_Longitude>-0.390125</Location_Longitude>
		<Location_Latitude>51.535960</Location_Latitude>
	</Route_Geometry>
	<Route_Geometry aContract_Line_No="X140" aLBSL_Run_No="2" aSequence_No="58">
		<Direction>2</Direction>
		<Location_Easting>511737</Location_Easting>
		<Location_Northing>183096</Location_Northing>
		<Location_Longitude>-0.390364</Location_Longitude>
		<Location_Latitude>51.535720</Location_Latitude>
	</Route_Geometry>
	<Route_Geometry aContract_Line_No="X140" aLBSL_Run_No="2" aSequence_No="59">
		<Direction>2</Direction>
		<Location_Easting>511707</Location_Easting>
		<Location_Northing>183088</Location_Northing>
		<Location_Longitude>-0.390799</Location_Longitude>
		<Location_Latitude>51.535654</Location_Latitude>
	</Route_Geometry>
	<Route_Geometry aContract_Line_No="X140" aLBSL_Run_No="2" aSequence_No="60">
		<Direction>2</Direction>
		<Location_Easting>511693</Location_Easting>
		<Location_Northing>183093</Location_Northing>
		<Location_Longitude>-0.390999</Location_Longitude>
		<Location_Latitude>51.535702</Location_Latitude>
	</Route_Geometry>
	<Route_Geometry aContract_Line_No="X140" aLBSL_Run_No="2" aSequence_No="61">
		<Direction>2</Direction>
		<Location_Easting>511674</Location_Easting>
		<Location_Northing>183116</Location_Northing>
		<Location_Longitude>-0.391266</Location_Longitude>
		<Location_Latitude>51.535913</Location_Latitude>
	</Route_Geometry>
	<Route_Geometry aContract_Line_No="X140" aLBSL_Run_No="2" aSequence_No="62">
		<Direction>2</Direction>
		<Location_Easting>511638</Location_Easting>
		<Location_Northing>183125</Location_Northing>
		<Location_Longitude>-0.391782</Location_Longitude>
		<Location_Latitude>51.536001</Location_Latitude>
	</Route_Geometry>
	<Route_Geometry aContract_Line_No="X140" aLBSL_Run_No="2" aSequence_No="63">
		<Direction>2</Direction>
		<Location_Easting>511527</Location_Easting>
		<Location_Northing>183069</Location_Northing>
		<Location_Longitude>-0.393399</Location_Longitude>
		<Location_Latitude>51.535519</Location_Latitude>
	</Route_Geometry>
	<Route_Geometry aContract_Line_No="X140" aLBSL_Run_No="2" aSequence_No="64">
		<Direction>2</Direction>
		<Location_Easting>511337</Location_Easting>
		<Location_Northing>182874</Location_Northing>
		<Location_Longitude>-0.396199</Location_Longitude>
		<Location_Latitude>51.533804</Location_Latitude>
	</Route_Geometry>
	<Route_Geometry aContract_Line_No="X140" aLBSL_Run_No="2" aSequence_No="65">
		<Direction>2</Direction>
		<Location_Easting>511306</Location_Easting>
		<Location_Northing>182820</Location_Northing>
		<Location_Longitude>-0.396663</Location_Longitude>
		<Location_Latitude>51.533325</Location_Latitude>
	</Route_Geometry>
	<Route_Geometry aContract_Line_No="X140" aLBSL_Run_No="2" aSequence_No="66">
		<Direction>2</Direction>
		<Location_Easting>511290</Location_Easting>
		<Location_Northing>182722</Location_Northing>
		<Location_Longitude>-0.396925</Location_Longitude>
		<Location_Latitude>51.532447</Location_Latitude>
	</Route_Geometry>
	<Route_Geometry aContract_Line_No="X140" aLBSL_Run_No="2" aSequence_No="67">
		<Direction>2</Direction>
		<Location_Easting>511291</Location_Easting>
		<Location_Northing>182653</Location_Northing>
		<Location_Longitude>-0.396932</Location_Longitude>
		<Location_Latitude>51.531827</Location_Latitude>
	</Route_Geometry>
	<Route_Geometry aContract_Line_No="X140" aLBSL_Run_No="2" aSequence_No="68">
		<Direction>2</Direction>
		<Location_Easting>511241</Location_Easting>
		<Location_Northing>182464</Location_Northing>
		<Location_Longitude>-0.397712</Location_Longitude>
		<Location_Latitude>51.530138</Location_Latitude>
	</Route_Geometry>
	<Route_Geometry aContract_Line_No="X140" aLBSL_Run_No="2" aSequence_No="69">
		<Direction>2</Direction>
		<Location_Easting>511162</Location_Easting>
		<Location_Northing>182274</Location_Northing>
		<Location_Longitude>-0.398911</Location_Longitude>
		<Location_Latitude>51.528446</Location_Latitude>
	</Route_Geometry>
	<Route_Geometry aContract_Line_No="X140" aLBSL_Run_No="2" aSequence_No="70">
		<Direction>2</Direction>
		<Location_Easting>511141</Location_Easting>
		<Location_Northing>182169</Location_Northing>
		<Location_Longitude>-0.399246</Location_Longitude>
		<Location_Latitude>51.527506</Location_Latitude>
	</Route_Geometry>
	<Route_Geometry aContract_Line_No="X140" aLBSL_Run_No="2" aSequence_No="71">
		<Direction>2</Direction>
		<Location_Easting>511160</Location_Easting>
		<Location_Northing>182000</Location_Northing>
		<Location_Longitude>-0.399026</Location_Longitude>
		<Location_Latitude>51.525983</Location_Latitude>
	</Route_Geometry>
	<Route_Geometry aContract_Line_No="X140" aLBSL_Run_No="2" aSequence_No="72">
		<Direction>2</Direction>
		<Location_Easting>511154</Location_Easting>
		<Location_Northing>181875</Location_Northing>
		<Location_Longitude>-0.399152</Location_Longitude>
		<Location_Latitude>51.524861</Location_Latitude>
	</Route_Geometry>
	<Route_Geometry aContract_Line_No="X140" aLBSL_Run_No="2" aSequence_No="73">
		<Direction>2</Direction>
		<Location_Easting>511097</Location_Easting>
		<Location_Northing>181721</Location_Northing>
		<Location_Longitude>-0.400021</Location_Longitude>
		<Location_Latitude>51.523488</Location_Latitude>
	</Route_Geometry>
	<Route_Geometry aContract_Line_No="X140" aLBSL_Run_No="2" aSequence_No="74">
		<Direction>2</Direction>
		<Location_Easting>510986</Location_Easting>
		<Location_Northing>181558</Location_Northing>
		<Location_Longitude>-0.401672</Location_Longitude>
		<Location_Latitude>51.522045</Location_Latitude>
	</Route_Geometry>
	<Route_Geometry aContract_Line_No="X140" aLBSL_Run_No="2" aSequence_No="75">
		<Direction>2</Direction>
		<Location_Easting>510862</Location_Easting>
		<Location_Northing>181419</Location_Northing>
		<Location_Longitude>-0.403502</Location_Longitude>
		<Location_Latitude>51.520820</Location_Latitude>
	</Route_Geometry>
	<Route_Geometry aContract_Line_No="X140" aLBSL_Run_No="2" aSequence_No="76">
		<Direction>2</Direction>
		<Location_Easting>510745</Location_Easting>
		<Location_Northing>181307</Location_Northing>
		<Location_Longitude>-0.405223</Location_Longitude>
		<Location_Latitude>51.519836</Location_Latitude>
	</Route_Geometry>
	<Route_Geometry aContract_Line_No="X140" aLBSL_Run_No="2" aSequence_No="77">
		<Direction>2</Direction>
		<Location_Easting>510655</Location_Easting>
		<Location_Northing>181115</Location_Northing>
		<Location_Longitude>-0.406580</Location_Longitude>
		<Location_Latitude>51.518128</Location_Latitude>
	</Route_Geometry>
	<Route_Geometry aContract_Line_No="X140" aLBSL_Run_No="2" aSequence_No="78">
		<Direction>2</Direction>
		<Location_Easting>510656</Location_Easting>
		<Location_Northing>181091</Location_Northing>
		<Location_Longitude>-0.406573</Location_Longitude>
		<Location_Latitude>51.517912</Location_Latitude>
	</Route_Geometry>
	<Route_Geometry aContract_Line_No="X140" aLBSL_Run_No="2" aSequence_No="79">
		<Direction>2</Direction>
		<Location_Easting>510629</Location_Easting>
		<Location_Northing>181040</Location_Northing>
		<Location_Longitude>-0.406978</Location_Longitude>
		<Location_Latitude>51.517459</Location_Latitude>
	</Route_Geometry>
	<Route_Geometry aContract_Line_No="X140" aLBSL_Run_No="2" aSequence_No="80">
		<Direction>2</Direction>
		<Location_Easting>510581</Location_Easting>
		<Location_Northing>180993</Location_Northing>
		<Location_Longitude>-0.407685</Location_Longitude>
		<Location_Latitude>51.517046</Location_Latitude>
	</Route_Geometry>
	<Route_Geometry aContract_Line_No="X140" aLBSL_Run_No="2" aSequence_No="81">
		<Direction>2</Direction>
		<Location_Easting>510532</Location_Easting>
		<Location_Northing>180967</Location_Northing>
		<Location_Longitude>-0.408399</Location_Longitude>
		<Location_Latitude>51.516822</Location_Latitude>
	</Route_Geometry>
	<Route_Geometry aContract_Line_No="X140" aLBSL_Run_No="2" aSequence_No="82">
		<Direction>2</Direction>
		<Location_Easting>510378</Location_Easting>
		<Location_Northing>180650</Location_Northing>
		<Location_Longitude>-0.410716</Location_Longitude>
		<Location_Latitude>51.514003</Location_Latitude>
	</Route_Geometry>
	<Route_Geometry aContract_Line_No="X140" aLBSL_Run_No="2" aSequence_No="83">
		<Direction>2</Direction>
		<Location_Easting>510324</Location_Easting>
		<Location_Northing>180556</Location_Northing>
		<Location_Longitude>-0.411524</Location_Longitude>
		<Location_Latitude>51.513169</Location_Latitude>
	</Route_Geometry>
	<Route_Geometry aContract_Line_No="X140" aLBSL_Run_No="2" aSequence_No="84">
		<Direction>2</Direction>
		<Location_Easting>510278</Location_Easting>
		<Location_Northing>180455</Location_Northing>
		<Location_Longitude>-0.412218</Location_Longitude>
		<Location_Latitude>51.512270</Location_Latitude>
	</Route_Geometry>
	<Route_Geometry aContract_Line_No="X140" aLBSL_Run_No="2" aSequence_No="85">
		<Direction>2</Direction>
		<Location_Easting>510147</Location_Easting>
		<Location_Northing>180229</Location_Northing>
		<Location_Longitude>-0.414176</Location_Longitude>
		<Location_Latitude>51.510264</Location_Latitude>
	</Route_Geometry>
	<Route_Geometry aContract_Line_No="X140" aLBSL_Run_No="2" aSequence_No="86">
		<Direction>2</Direction>
		<Location_Easting>510115</Location_Easting>
		<Location_Northing>180193</Location_Northing>
		<Location_Longitude>-0.414648</Location_Longitude>
		<Location_Latitude>51.509947</Location_Latitude>
	</Route_Geometry>
	<Route_Geometry aContract_Line_No="X140" aLBSL_Run_No="2" aSequence_No="87">
		<Direction>2</Direction>
		<Location_Easting>509992</Location_Easting>
		<Location_Northing>179979</Location_Northing>
		<Location_Longitude>-0.416486</Location_Longitude>
		<Location_Latitude>51.508047</Location_Latitude>
	</Route_Geometry>
	<Route_Geometry aContract_Line_No="X140" aLBSL_Run_No="2" aSequence_No="88">
		<Direction>2</Direction>
		<Location_Easting>509937</Location_Easting>
		<Location_Northing>179918</Location_Northing>
		<Location_Longitude>-0.417297</Location_Longitude>
		<Location_Latitude>51.507510</Location_Latitude>
	</Route_Geometry>
	<Route_Geometry aContract_Line_No="X140" aLBSL_Run_No="2" aSequence_No="89">
		<Direction>2</Direction>
		<Location_Easting>509906</Location_Easting>
		<Location_Northing>179898</Location_Northing>
		<Location_Longitude>-0.417750</Location_Longitude>
		<Location_Latitude>51.507336</Location_Latitude>
	</Route_Geometry>
	<Route_Geometry aContract_Line_No="X140" aLBSL_Run_No="2" aSequence_No="90">
		<Direction>2</Direction>
		<Location_Easting>509901</Location_Easting>
		<Location_Northing>179886</Location_Northing>
		<Location_Longitude>-0.417826</Location_Longitude>
		<Location_Latitude>51.507229</Location_Latitude>
	</Route_Geometry>
	<Route_Geometry aContract_Line_No="X140" aLBSL_Run_No="2" aSequence_No="91">
		<Direction>2</Direction>
		<Location_Easting>509890</Location_Easting>
		<Location_Northing>179892</Location_Northing>
		<Location_Longitude>-0.417982</Location_Longitude>
		<Location_Latitude>51.507285</Location_Latitude>
	</Route_Geometry>
	<Route_Geometry aContract_Line_No="X140" aLBSL_Run_No="2" aSequence_No="92">
		<Direction>2</Direction>
		<Location_Easting>509843</Location_Easting>
		<Location_Northing>179876</Location_Northing>
		<Location_Longitude>-0.418664</Location_Longitude>
		<Location_Latitude>51.507150</Location_Latitude>
	</Route_Geometry>
	<Route_Geometry aContract_Line_No="X140" aLBSL_Run_No="2" aSequence_No="93">
		<Direction>2</Direction>
		<Location_Easting>509843</Location_Easting>
		<Location_Northing>179848</Location_Northing>
		<Location_Longitude>-0.418673</Location_Longitude>
		<Location_Latitude>51.506899</Location_Latitude>
	</Route_Geometry>
	<Route_Geometry aContract_Line_No="X140" aLBSL_Run_No="2" aSequence_No="94">
		<Direction>2</Direction>
		<Location_Easting>509822</Location_Easting>
		<Location_Northing>179825</Location_Northing>
		<Location_Longitude>-0.418983</Location_Longitude>
		<Location_Latitude>51.506696</Location_Latitude>
	</Route_Geometry>
	<Route_Geometry aContract_Line_No="X140" aLBSL_Run_No="2" aSequence_No="95">
		<Direction>2</Direction>
		<Location_Easting>509817</Location_Easting>
		<Location_Northing>179670</Location_Northing>
		<Location_Longitude>-0.419103</Location_Longitude>
		<Location_Latitude>51.505304</Location_Latitude>
	</Route_Geometry>
	<Route_Geometry aContract_Line_No="X140" aLBSL_Run_No="2" aSequence_No="96">
		<Direction>2</Direction>
		<Location_Easting>509766</Location_Easting>
		<Location_Northing>179546</Location_Northing>
		<Location_Longitude>-0.419876</Location_Longitude>
		<Location_Latitude>51.504199</Location_Latitude>
	</Route_Geometry>
	<Route_Geometry aContract_Line_No="X140" aLBSL_Run_No="2" aSequence_No="97">
		<Direction>2</Direction>
		<Location_Easting>509770</Location_Easting>
		<Location_Northing>179540</Location_Northing>
		<Location_Longitude>-0.419820</Location_Longitude>
		<Location_Latitude>51.504144</Location_Latitude>
	</Route_Geometry>
	<Route_Geometry aContract_Line_No="X140" aLBSL_Run_No="2" aSequence_No="98">
		<Direction>2</Direction>
		<Location_Easting>509761</Location_Easting>
		<Location_Northing>179535</Location_Northing>
		<Location_Longitude>-0.419951</Location_Longitude>
		<Location_Latitude>51.504101</Location_Latitude>
	</Route_Geometry>
	<Route_Geometry aContract_Line_No="X140" aLBSL_Run_No="2" aSequence_No="99">
		<Direction>2</Direction>
		<Location_Easting>509715</Location_Easting>
		<Location_Northing>179446</Location_Northing>
		<Location_Longitude>-0.420641</Location_Longitude>
		<Location_Latitude>51.503310</Location_Latitude>
	</Route_Geometry>
	<Route_Geometry aContract_Line_No="X140" aLBSL_Run_No="2" aSequence_No="100">
		<Direction>2</Direction>
		<Location_Easting>509660</Location_Easting>
		<Location_Northing>179365</Location_Northing>
		<Location_Longitude>-0.421459</Location_Longitude>
		<Location_Latitude>51.502593</Location_Latitude>
	</Route_Geometry>
	<Route_Geometry aContract_Line_No="X140" aLBSL_Run_No="2" aSequence_No="101">
		<Direction>2</Direction>
		<Location_Easting>509535</Location_Easting>
		<Location_Northing>179280</Location_Northing>
		<Location_Longitude>-0.423285</Location_Longitude>
		<Location_Latitude>51.501853</Location_Latitude>
	</Route_Geometry>
	<Route_Geometry aContract_Line_No="X140" aLBSL_Run_No="2" aSequence_No="102">
		<Direction>2</Direction>
		<Location_Easting>509490</Location_Easting>
		<Location_Northing>179223</Location_Northing>
		<Location_Longitude>-0.423951</Location_Longitude>
		<Location_Latitude>51.501349</Location_Latitude>
	</Route_Geometry>
	<Route_Geometry aContract_Line_No="X140" aLBSL_Run_No="2" aSequence_No="103">
		<Direction>2</Direction>
		<Location_Easting>509301</Location_Easting>
		<Location_Northing>178794</Location_Northing>
		<Location_Longitude>-0.426806</Location_Longitude>
		<Location_Latitude>51.497530</Location_Latitude>
	</Route_Geometry>
	<Route_Geometry aContract_Line_No="X140" aLBSL_Run_No="2" aSequence_No="104">
		<Direction>2</Direction>
		<Location_Easting>509223</Location_Easting>
		<Location_Northing>178592</Location_Northing>
		<Location_Longitude>-0.427991</Location_Longitude>
		<Location_Latitude>51.495730</Location_Latitude>
	</Route_Geometry>
	<Route_Geometry aContract_Line_No="X140" aLBSL_Run_No="2" aSequence_No="105">
		<Direction>2</Direction>
		<Location_Easting>509201</Location_Easting>
		<Location_Northing>178500</Location_Northing>
		<Location_Longitude>-0.428336</Location_Longitude>
		<Location_Latitude>51.494907</Location_Latitude>
	</Route_Geometry>
	<Route_Geometry aContract_Line_No="X140" aLBSL_Run_No="2" aSequence_No="106">
		<Direction>2</Direction>
		<Location_Easting>509168</Location_Easting>
		<Location_Northing>178287</Location_Northing>
		<Location_Longitude>-0.428878</Location_Longitude>
		<Location_Latitude>51.492999</Location_Latitude>
	</Route_Geometry>
	<Route_Geometry aContract_Line_No="X140" aLBSL_Run_No="2" aSequence_No="107">
		<Direction>2</Direction>
		<Location_Easting>509154</Location_Easting>
		<Location_Northing>178259</Location_Northing>
		<Location_Longitude>-0.429088</Location_Longitude>
		<Location_Latitude>51.492750</Location_Latitude>
	</Route_Geometry>
	<Route_Geometry aContract_Line_No="X140" aLBSL_Run_No="2" aSequence_No="108">
		<Direction>2</Direction>
		<Location_Easting>509107</Location_Easting>
		<Location_Northing>178209</Location_Northing>
		<Location_Longitude>-0.429780</Location_Longitude>
		<Location_Latitude>51.492309</Location_Latitude>
	</Route_Geometry>
	<Route_Geometry aContract_Line_No="X140" aLBSL_Run_No="2" aSequence_No="109">
		<Direction>2</Direction>
		<Location_Easting>509076</Location_Easting>
		<Location_Northing>178194</Location_Northing>
		<Location_Longitude>-0.430231</Location_Longitude>
		<Location_Latitude>51.492181</Location_Latitude>
	</Route_Geometry>
	<Route_Geometry aContract_Line_No="X140" aLBSL_Run_No="2" aSequence_No="110">
		<Direction>2</Direction>
		<Location_Easting>508870</Location_Easting>
		<Location_Northing>178155</Location_Northing>
		<Location_Longitude>-0.433209</Location_Longitude>
		<Location_Latitude>51.491870</Location_Latitude>
	</Route_Geometry>
	<Route_Geometry aContract_Line_No="X140" aLBSL_Run_No="2" aSequence_No="111">
		<Direction>2</Direction>
		<Location_Easting>508830</Location_Easting>
		<Location_Northing>178132</Location_Northing>
		<Location_Longitude>-0.433792</Location_Longitude>
		<Location_Latitude>51.491671</Location_Latitude>
	</Route_Geometry>
	<Route_Geometry aContract_Line_No="X140" aLBSL_Run_No="2" aSequence_No="112">
		<Direction>2</Direction>
		<Location_Easting>508794</Location_Easting>
		<Location_Northing>178090</Location_Northing>
		<Location_Longitude>-0.434323</Location_Longitude>
		<Location_Latitude>51.491300</Location_Latitude>
	</Route_Geometry>
	<Route_Geometry aContract_Line_No="X140" aLBSL_Run_No="2" aSequence_No="113">
		<Direction>2</Direction>
		<Location_Easting>508696</Location_Easting>
		<Location_Northing>177702</Location_Northing>
		<Location_Longitude>-0.435854</Location_Longitude>
		<Location_Latitude>51.487832</Location_Latitude>
	</Route_Geometry>
	<Route_Geometry aContract_Line_No="X140" aLBSL_Run_No="2" aSequence_No="114">
		<Direction>2</Direction>
		<Location_Easting>508712</Location_Easting>
		<Location_Northing>177605</Location_Northing>
		<Location_Longitude>-0.435653</Location_Longitude>
		<Location_Latitude>51.486957</Location_Latitude>
	</Route_Geometry>
	<Route_Geometry aContract_Line_No="X140" aLBSL_Run_No="2" aSequence_No="115">
		<Direction>2</Direction>
		<Location_Easting>508775</Location_Easting>
		<Location_Northing>177464</Location_Northing>
		<Location_Longitude>-0.434789</Location_Longitude>
		<Location_Latitude>51.485677</Location_Latitude>
	</Route_Geometry>
	<Route_Geometry aContract_Line_No="X140" aLBSL_Run_No="2" aSequence_No="116">
		<Direction>2</Direction>
		<Location_Easting>508809</Location_Easting>
		<Location_Northing>177363</Location_Northing>
		<Location_Longitude>-0.434331</Location_Longitude>
		<Location_Latitude>51.484763</Location_Latitude>
	</Route_Geometry>
	<Route_Geometry aContract_Line_No="X140" aLBSL_Run_No="2" aSequence_No="117">
		<Direction>2</Direction>
		<Location_Easting>508826</Location_Easting>
		<Location_Northing>177225</Location_Northing>
		<Location_Longitude>-0.434129</Location_Longitude>
		<Location_Latitude>51.483519</Location_Latitude>
	</Route_Geometry>
	<Route_Geometry aContract_Line_No="X140" aLBSL_Run_No="2" aSequence_No="118">
		<Direction>2</Direction>
		<Location_Easting>508818</Location_Easting>
		<Location_Northing>176984</Location_Northing>
		<Location_Longitude>-0.434318</Location_Longitude>
		<Location_Latitude>51.481354</Location_Latitude>
	</Route_Geometry>
	<Route_Geometry aContract_Line_No="X140" aLBSL_Run_No="2" aSequence_No="119">
		<Direction>2</Direction>
		<Location_Easting>508828</Location_Easting>
		<Location_Northing>176902</Location_Northing>
		<Location_Longitude>-0.434199</Location_Longitude>
		<Location_Latitude>51.480615</Location_Latitude>
	</Route_Geometry>
	<Route_Geometry aContract_Line_No="X140" aLBSL_Run_No="2" aSequence_No="120">
		<Direction>2</Direction>
		<Location_Easting>507848</Location_Easting>
		<Location_Northing>176939</Location_Northing>
		<Location_Longitude>-0.448295</Location_Longitude>
		<Location_Latitude>51.481136</Location_Latitude>
	</Route_Geometry>
	<Route_Geometry aContract_Line_No="X140" aLBSL_Run_No="2" aSequence_No="121">
		<Direction>2</Direction>
		<Location_Easting>507847</Location_Easting>
		<Location_Northing>176922</Location_Northing>
		<Location_Longitude>-0.448315</Location_Longitude>
		<Location_Latitude>51.480983</Location_Latitude>
	</Route_Geometry>
	<Route_Geometry aContract_Line_No="X140" aLBSL_Run_No="2" aSequence_No="122">
		<Direction>2</Direction>
		<Location_Easting>507792</Location_Easting>
		<Location_Northing>176896</Location_Northing>
		<Location_Longitude>-0.449114</Location_Longitude>
		<Location_Latitude>51.480760</Location_Latitude>
	</Route_Geometry>
	<Route_Geometry aContract_Line_No="X140" aLBSL_Run_No="2" aSequence_No="123">
		<Direction>2</Direction>
		<Location_Easting>507776</Location_Easting>
		<Location_Northing>176857</Location_Northing>
		<Location_Longitude>-0.449356</Location_Longitude>
		<Location_Latitude>51.480413</Location_Latitude>
	</Route_Geometry>
	<Route_Geometry aContract_Line_No="X140" aLBSL_Run_No="2" aSequence_No="124">
		<Direction>2</Direction>
		<Location_Easting>507754</Location_Easting>
		<Location_Northing>176852</Location_Northing>
		<Location_Longitude>-0.449675</Location_Longitude>
		<Location_Latitude>51.480372</Location_Latitude>
	</Route_Geometry>
	<Route_Geometry aContract_Line_No="X140" aLBSL_Run_No="2" aSequence_No="125">
		<Direction>2</Direction>
		<Location_Easting>507739</Location_Easting>
		<Location_Northing>176862</Location_Northing>
		<Location_Longitude>-0.449888</Location_Longitude>
		<Location_Latitude>51.480464</Location_Latitude>
	</Route_Geometry>
	<Route_Geometry aContract_Line_No="X140" aLBSL_Run_No="2" aSequence_No="126">
		<Direction>2</Direction>
		<Location_Easting>507686</Location_Easting>
		<Location_Northing>176865</Location_Northing>
		<Location_Longitude>-0.450649</Location_Longitude>
		<Location_Latitude>51.480502</Location_Latitude>
	</Route_Geometry>
	<Route_Geometry aContract_Line_No="X140" aLBSL_Run_No="2" aSequence_No="127">
		<Direction>2</Direction>
		<Location_Easting>507607</Location_Easting>
		<Location_Northing>176893</Location_Northing>
		<Location_Longitude>-0.451778</Location_Longitude>
		<Location_Latitude>51.480768</Location_Latitude>
	</Route_Geometry>
	<Route_Geometry aContract_Line_No="X140" aLBSL_Run_No="2" aSequence_No="128">
		<Direction>2</Direction>
		<Location_Easting>507551</Location_Easting>
		<Location_Northing>176875</Location_Northing>
		<Location_Longitude>-0.452590</Location_Longitude>
		<Location_Latitude>51.480617</Location_Latitude>
	</Route_Geometry>
	<Route_Geometry aContract_Line_No="X140" aLBSL_Run_No="2" aSequence_No="129">
		<Direction>2</Direction>
		<Location_Easting>507531</Location_Easting>
		<Location_Northing>176833</Location_Northing>
		<Location_Longitude>-0.452891</Location_Longitude>
		<Location_Latitude>51.480243</Location_Latitude>
	</Route_Geometry>
	<Route_Geometry aContract_Line_No="X140" aLBSL_Run_No="2" aSequence_No="130">
		<Direction>2</Direction>
		<Location_Easting>507547</Location_Easting>
		<Location_Northing>176178</Location_Northing>
		<Location_Longitude>-0.452859</Location_Longitude>
		<Location_Latitude>51.474353</Location_Latitude>
	</Route_Geometry>
	<Route_Geometry aContract_Line_No="X140" aLBSL_Run_No="2" aSequence_No="131">
		<Direction>2</Direction>
		<Location_Easting>507544</Location_Easting>
		<Location_Northing>175986</Location_Northing>
		<Location_Longitude>-0.452961</Location_Longitude>
		<Location_Latitude>51.472628</Location_Latitude>
	</Route_Geometry>
	<Route_Geometry aContract_Line_No="X140" aLBSL_Run_No="2" aSequence_No="132">
		<Direction>2</Direction>
		<Location_Easting>507561</Location_Easting>
		<Location_Northing>175926</Location_Northing>
		<Location_Longitude>-0.452734</Location_Longitude>
		<Location_Latitude>51.472085</Location_Latitude>
	</Route_Geometry>
	<Route_Geometry aContract_Line_No="X140" aLBSL_Run_No="2" aSequence_No="133">
		<Direction>2</Direction>
		<Location_Easting>507574</Location_Easting>
		<Location_Northing>175906</Location_Northing>
		<Location_Longitude>-0.452553</Location_Longitude>
		<Location_Latitude>51.471903</Location_Latitude>
	</Route_Geometry>
	<Route_Geometry aContract_Line_No="X140" aLBSL_Run_No="2" aSequence_No="134">
		<Direction>2</Direction>
		<Location_Easting>507575</Location_Easting>
		<Location_Northing>175888</Location_Northing>
		<Location_Longitude>-0.452544</Location_Longitude>
		<Location_Latitude>51.471741</Location_Latitude>
	</Route_Geometry>
	<Route_Geometry aContract_Line_No="X140" aLBSL_Run_No="2" aSequence_No="135">
		<Direction>2</Direction>
		<Location_Easting>507568</Location_Easting>
		<Location_Northing>175862</Location_Northing>
		<Location_Longitude>-0.452653</Location_Longitude>
		<Location_Latitude>51.471509</Location_Latitude>
	</Route_Geometry>
	<Route_Geometry aContract_Line_No="X140" aLBSL_Run_No="2" aSequence_No="136">
		<Direction>2</Direction>
		<Location_Easting>507561</Location_Easting>
		<Location_Northing>175853</Location_Northing>
		<Location_Longitude>-0.452756</Location_Longitude>
		<Location_Latitude>51.471429</Location_Latitude>
	</Route_Geometry>
	<Route_Geometry aContract_Line_No="X140" aLBSL_Run_No="2" aSequence_No="137">
		<Direction>2</Direction>
		<Location_Easting>507551</Location_Easting>
		<Location_Northing>175848</Location_Northing>
		<Location_Longitude>-0.452902</Location_Longitude>
		<Location_Latitude>51.471386</Location_Latitude>
	</Route_Geometry>
</rg:Network_Data>
